[
{
    "model": "product.product",
    "pk": 111366,
    "fields": {
        "code": "3501940000213",
        "product_name": "P\u00e2te \u00e0 Tartiner Noisettes Chocolat Noir",
        "brands": "Bovetti",
        "categories": "Produits \u00e0 tartiner,Petit-d\u00e9jeuners,Produits \u00e0 tartiner sucr\u00e9s,P\u00e2tes \u00e0 tartiner,P\u00e2tes \u00e0 tartiner au chocolat,P\u00e2tes \u00e0 tartiner aux noisettes,P\u00e2tes \u00e0 tartiner aux noisettes et au cacao",
        "nutrition_grades": "e",
        "url": "https://fr.openfoodfacts.org/produit/3501940000213/pate-a-tartiner-noisettes-chocolat-noir-bovetti",
        "image_url": "https://static.openfoodfacts.org/images/products/350/194/000/0213/front_fr.10.400.jpg",
        "image_small_url": "https://static.openfoodfacts.org/images/products/350/194/000/0213/front_fr.10.200.jpg",
        "fat": "high",
        "salt": "low",
        "saturated_fat": "high",
        "sugars": "high",
        "fat_100g": 48,
        "saturated_fat_100g": 10,
        "sugars_100g": 32,
        "salt_100g": 0
    }
},
{
    "model": "product.product",
    "pk": 111187,
    "fields": {
        "code": "3501940800004",
        "product_name": "Veritable p\u00e2te \u00e0 tartiner Noisettes - Chocolat noir",
        "brands": "Bovetti",
        "categories": "Produits \u00e0 tartiner,Petit-d\u00e9jeuners,Produits \u00e0 tartiner sucr\u00e9s,P\u00e2tes \u00e0 tartiner,P\u00e2tes \u00e0 tartiner au chocolat,P\u00e2tes \u00e0 tartiner aux noisettes,P\u00e2tes \u00e0 tartiner aux noisettes et au cacao",
        "nutrition_grades": "e",
        "url": "https://fr.openfoodfacts.org/produit/3501940800004/veritable-pate-a-tartiner-noisettes-chocolat-noir-bovetti",
        "image_url": "https://static.openfoodfacts.org/images/products/350/194/080/0004/front_fr.6.400.jpg",
        "image_small_url": "https://static.openfoodfacts.org/images/products/350/194/080/0004/front_fr.6.200.jpg",
        "fat": "high",
        "salt": "low",
        "saturated_fat": "high",
        "sugars": "high",
        "fat_100g": 48,
        "saturated_fat_100g": 10,
        "sugars_100g": 32,
        "salt_100g": 0
    }
},
{
    "model": "product.product",
    "pk": 111051,
    "fields": {
        "code": "3564700088753",
        "product_name": "Nustikao ",
        "brands": "Nustikao,Marque Rep\u00e8re",
        "categories": "Produits \u00e0 tartiner,Petit-d\u00e9jeuners,Produits \u00e0 tartiner sucr\u00e9s,P\u00e2tes \u00e0 tartiner,P\u00e2tes \u00e0 tartiner au chocolat,P\u00e2tes \u00e0 tartiner aux noisettes,P\u00e2tes \u00e0 tartiner aux noisettes et au cacao",
        "nutrition_grades": "e",
        "url": "https://fr.openfoodfacts.org/produit/3564700088753/nustikao",
        "image_url": "https://static.openfoodfacts.org/images/products/356/470/008/8753/front_fr.7.400.jpg",
        "image_small_url": "https://static.openfoodfacts.org/images/products/356/470/008/8753/front_fr.7.200.jpg",
        "fat": "high",
        "salt": "low",
        "saturated_fat": "high",
        "sugars": "high",
        "fat_100g": 29,
        "saturated_fat_100g": 10,
        "sugars_100g": 58,
        "salt_100g": 0
    }
},
{
    "model": "product.product",
    "pk": 110514,
    "fields": {
        "code": "3560071009717",
        "product_name": "Squiiiz p\u00e2te \u00e0 tartiner noisettes",
        "brands": "Carrefour",
        "categories": "Produits \u00e0 tartiner,Petit-d\u00e9jeuners,Produits \u00e0 tartiner sucr\u00e9s,P\u00e2tes \u00e0 tartiner,P\u00e2tes \u00e0 tartiner au chocolat,P\u00e2tes \u00e0 tartiner aux noisettes,P\u00e2tes \u00e0 tartiner aux noisettes et au cacao",
        "nutrition_grades": "e",
        "url": "https://fr.openfoodfacts.org/produit/3560071009717/squiiiz-pate-a-tartiner-noisettes-carrefour",
        "image_url": "https://static.openfoodfacts.org/images/products/356/007/100/9717/front_fr.5.400.jpg",
        "image_small_url": "https://static.openfoodfacts.org/images/products/356/007/100/9717/front_fr.5.200.jpg",
        "fat": "high",
        "salt": "low",
        "saturated_fat": "high",
        "sugars": "high",
        "fat_100g": 29,
        "saturated_fat_100g": 10,
        "sugars_100g": 57,
        "salt_100g": 0
    }
},
{
    "model": "product.product",
    "pk": 109408,
    "fields": {
        "code": "3266191006680",
        "product_name": "P\u00e2te \u00e0 tartiner Noisette Cacao",
        "brands": "La Vie Claire",
        "categories": "Produits \u00e0 tartiner,Petit-d\u00e9jeuners,Produits \u00e0 tartiner sucr\u00e9s,P\u00e2tes \u00e0 tartiner,P\u00e2tes \u00e0 tartiner au chocolat,P\u00e2tes \u00e0 tartiner aux noisettes,P\u00e2tes \u00e0 tartiner aux noisettes et au cacao",
        "nutrition_grades": "e",
        "url": "https://fr.openfoodfacts.org/produit/3266191006680/pate-a-tartiner-noisette-cacao-la-vie-claire",
        "image_url": "https://static.openfoodfacts.org/images/products/326/619/100/6680/front_fr.3.400.jpg",
        "image_small_url": "https://static.openfoodfacts.org/images/products/326/619/100/6680/front_fr.3.200.jpg",
        "fat": "high",
        "salt": "low",
        "saturated_fat": "high",
        "sugars": "high",
        "fat_100g": 46,
        "saturated_fat_100g": 17,
        "sugars_100g": 39,
        "salt_100g": 0
    }
},
{
    "model": "product.product",
    "pk": 107508,
    "fields": {
        "code": "3501940368009",
        "product_name": "V\u00e9ritable P\u00e2te \u00e0 tartiner Bio, Chocolat au lait - Noisettes",
        "brands": "Bovetti",
        "categories": "Petit-d\u00e9jeuners,Produits \u00e0 tartiner,Produits \u00e0 tartiner sucr\u00e9s,P\u00e2tes \u00e0 tartiner,P\u00e2tes \u00e0 tartiner au chocolat,P\u00e2tes \u00e0 tartiner aux noisettes,P\u00e2tes \u00e0 tartiner aux noisettes et au cacao",
        "nutrition_grades": "e",
        "url": "https://fr.openfoodfacts.org/produit/3501940368009/veritable-pate-a-tartiner-bio-chocolat-au-lait-noisettes-bovetti",
        "image_url": "https://static.openfoodfacts.org/images/products/350/194/036/8009/front_fr.10.400.jpg",
        "image_small_url": "https://static.openfoodfacts.org/images/products/350/194/036/8009/front_fr.10.200.jpg",
        "fat": "high",
        "salt": "low",
        "saturated_fat": "high",
        "sugars": "high",
        "fat_100g": 50,
        "saturated_fat_100g": 9,
        "sugars_100g": 33,
        "salt_100g": 0
    }
},
{
    "model": "product.product",
    "pk": 105875,
    "fields": {
        "code": "4104420037366",
        "product_name": "Nuss-Nougat",
        "brands": "Alnatura",
        "categories": "Produits \u00e0 tartiner,Petit-d\u00e9jeuners,Produits \u00e0 tartiner sucr\u00e9s,P\u00e2tes \u00e0 tartiner,P\u00e2tes \u00e0 tartiner au chocolat,P\u00e2tes \u00e0 tartiner aux noisettes,P\u00e2tes \u00e0 tartiner aux noisettes et au cacao",
        "nutrition_grades": "e",
        "url": "https://fr.openfoodfacts.org/produit/4104420037366/nuss-nougat-alnatura",
        "image_url": "https://static.openfoodfacts.org/images/products/410/442/003/7366/front_fr.20.400.jpg",
        "image_small_url": "https://static.openfoodfacts.org/images/products/410/442/003/7366/front_fr.20.200.jpg",
        "fat": "high",
        "salt": "low",
        "saturated_fat": "high",
        "sugars": "high",
        "fat_100g": 38,
        "saturated_fat_100g": 6,
        "sugars_100g": 49,
        "salt_100g": 0
    }
},
{
    "model": "product.product",
    "pk": 97323,
    "fields": {
        "code": "3501940000206",
        "product_name": "P\u00e2te \u00e0 Tartiner v\u00e9ritable Chocolat au Lait et Noisettes",
        "brands": "Bovetti",
        "categories": "Produits \u00e0 tartiner,Petit-d\u00e9jeuners,Produits \u00e0 tartiner sucr\u00e9s,P\u00e2tes \u00e0 tartiner,P\u00e2tes \u00e0 tartiner au chocolat,P\u00e2tes \u00e0 tartiner aux noisettes,P\u00e2tes \u00e0 tartiner aux noisettes et au cacao",
        "nutrition_grades": "e",
        "url": "https://fr.openfoodfacts.org/produit/3501940000206/pate-a-tartiner-veritable-chocolat-au-lait-et-noisettes-bovetti",
        "image_url": "https://static.openfoodfacts.org/images/products/350/194/000/0206/front_fr.14.400.jpg",
        "image_small_url": "https://static.openfoodfacts.org/images/products/350/194/000/0206/front_fr.14.200.jpg",
        "fat": "high",
        "salt": "low",
        "saturated_fat": "high",
        "sugars": "high",
        "fat_100g": 48,
        "saturated_fat_100g": 9,
        "sugars_100g": 32,
        "salt_100g": 0
    }
},
{
    "model": "product.product",
    "pk": 91955,
    "fields": {
        "code": "3383674400244",
        "product_name": "P\u00e2te \u00e0 tartiner au lait frais Chocolat Noisette",
        "brands": "Raffol\u00e9",
        "categories": "Produits \u00e0 tartiner,Petit-d\u00e9jeuners,Produits \u00e0 tartiner sucr\u00e9s,P\u00e2tes \u00e0 tartiner,P\u00e2tes \u00e0 tartiner au chocolat,P\u00e2tes \u00e0 tartiner aux noisettes,P\u00e2tes \u00e0 tartiner aux noisettes et au cacao",
        "nutrition_grades": "d",
        "url": "https://fr.openfoodfacts.org/produit/3383674400244/pate-a-tartiner-au-lait-frais-chocolat-noisette-raffole",
        "image_url": "https://static.openfoodfacts.org/images/products/338/367/440/0244/front_fr.10.400.jpg",
        "image_small_url": "https://static.openfoodfacts.org/images/products/338/367/440/0244/front_fr.10.200.jpg",
        "fat": "moderate",
        "salt": "low",
        "saturated_fat": "moderate",
        "sugars": "high",
        "fat_100g": 6,
        "saturated_fat_100g": 2,
        "sugars_100g": 44,
        "salt_100g": 0
    }
},
{
    "model": "product.product",
    "pk": 90389,
    "fields": {
        "code": "3339334700070",
        "product_name": "P\u00e2te \u00e0 tartiner Noisettes - Chocolat lait",
        "brands": "M. de Turenne",
        "categories": "Produits \u00e0 tartiner,Petit-d\u00e9jeuners,Produits \u00e0 tartiner sucr\u00e9s,P\u00e2tes \u00e0 tartiner,P\u00e2tes \u00e0 tartiner au chocolat,P\u00e2tes \u00e0 tartiner aux noisettes,P\u00e2tes \u00e0 tartiner aux noisettes et au cacao",
        "nutrition_grades": "e",
        "url": "https://fr.openfoodfacts.org/produit/3339334700070/pate-a-tartiner-noisettes-chocolat-lait-m-de-turenne",
        "image_url": "https://static.openfoodfacts.org/images/products/333/933/470/0070/front_fr.8.400.jpg",
        "image_small_url": "https://static.openfoodfacts.org/images/products/333/933/470/0070/front_fr.8.200.jpg",
        "fat": "high",
        "salt": "low",
        "saturated_fat": "high",
        "sugars": "high",
        "fat_100g": 48,
        "saturated_fat_100g": 9,
        "sugars_100g": 32,
        "salt_100g": 0
    }
},
{
    "model": "product.product",
    "pk": 89389,
    "fields": {
        "code": "3700662759366",
        "product_name": "P\u00e2te \u00e0 tartiner aux noisettes, chocolat noir et vanille",
        "brands": "",
        "categories": "Produits \u00e0 tartiner,Petit-d\u00e9jeuners,Produits \u00e0 tartiner sucr\u00e9s,P\u00e2tes \u00e0 tartiner,P\u00e2tes \u00e0 tartiner au chocolat,P\u00e2tes \u00e0 tartiner aux noisettes,P\u00e2tes \u00e0 tartiner aux noisettes et au cacao",
        "nutrition_grades": "e",
        "url": "https://fr.openfoodfacts.org/produit/3700662759366/pate-a-tartiner-aux-noisettes-chocolat-noir-et-vanille",
        "image_url": "https://static.openfoodfacts.org/images/products/370/066/275/9366/front_fr.4.400.jpg",
        "image_small_url": "https://static.openfoodfacts.org/images/products/370/066/275/9366/front_fr.4.200.jpg",
        "fat": "high",
        "salt": "low",
        "saturated_fat": "high",
        "sugars": "high",
        "fat_100g": 53,
        "saturated_fat_100g": 10,
        "sugars_100g": 27,
        "salt_100g": 0
    }
},
{
    "model": "product.product",
    "pk": 82561,
    "fields": {
        "code": "5413623704333",
        "product_name": "P\u00e2te \u00e0 Tartiner aux Noisettes et Cacao avec \u00c9dulcorants de St\u00e9via",
        "brands": "Cavalier",
        "categories": "Produits \u00e0 tartiner,Petit-d\u00e9jeuners,Produits \u00e0 tartiner sucr\u00e9s,P\u00e2tes \u00e0 tartiner,P\u00e2tes \u00e0 tartiner au chocolat,P\u00e2tes \u00e0 tartiner aux noisettes,P\u00e2tes \u00e0 tartiner aux noisettes et au cacao",
        "nutrition_grades": "c",
        "url": "https://fr.openfoodfacts.org/produit/5413623704333/pate-a-tartiner-aux-noisettes-et-cacao-avec-edulcorants-de-stevia-cavalier",
        "image_url": "https://static.openfoodfacts.org/images/products/541/362/370/4333/front_fr.3.400.jpg",
        "image_small_url": "https://static.openfoodfacts.org/images/products/541/362/370/4333/front_fr.3.200.jpg",
        "fat": "high",
        "salt": "low",
        "saturated_fat": "high",
        "sugars": "moderate",
        "fat_100g": 36,
        "saturated_fat_100g": 7,
        "sugars_100g": 7,
        "salt_100g": 0
    }
},
{
    "model": "product.product",
    "pk": 81401,
    "fields": {
        "code": "8710573442764",
        "product_name": "Nusica Chocolat Noisette",
        "brands": "Brinkers",
        "categories": "Produits \u00e0 tartiner,Petit-d\u00e9jeuners,Produits \u00e0 tartiner sucr\u00e9s,P\u00e2tes \u00e0 tartiner,P\u00e2tes \u00e0 tartiner au chocolat,P\u00e2tes \u00e0 tartiner aux noisettes,P\u00e2tes \u00e0 tartiner aux noisettes et au cacao",
        "nutrition_grades": "d",
        "url": "https://fr.openfoodfacts.org/produit/8710573442764/nusica-chocolat-noisette-brinkers",
        "image_url": "https://static.openfoodfacts.org/images/products/871/057/344/2764/front_fr.7.400.jpg",
        "image_small_url": "https://static.openfoodfacts.org/images/products/871/057/344/2764/front_fr.7.200.jpg",
        "fat": "high",
        "salt": "low",
        "saturated_fat": "moderate",
        "sugars": "high",
        "fat_100g": 33,
        "saturated_fat_100g": 5,
        "sugars_100g": 58,
        "salt_100g": 0
    }
},
{
    "model": "product.product",
    "pk": 77820,
    "fields": {
        "code": "3662072013370",
        "product_name": "P\u00e2te \u00e0 Tartiner",
        "brands": "So Tasty",
        "categories": "Produits \u00e0 tartiner,Petit-d\u00e9jeuners,Produits \u00e0 tartiner sucr\u00e9s,P\u00e2tes \u00e0 tartiner,P\u00e2tes \u00e0 tartiner au chocolat,P\u00e2tes \u00e0 tartiner aux noisettes,P\u00e2tes \u00e0 tartiner aux noisettes et au cacao",
        "nutrition_grades": "a",
        "url": "https://fr.openfoodfacts.org/produit/3662072013370/pate-a-tartiner-so-tasty",
        "image_url": "https://static.openfoodfacts.org/images/products/366/207/201/3370/front_fr.4.400.jpg",
        "image_small_url": "https://static.openfoodfacts.org/images/products/366/207/201/3370/front_fr.4.200.jpg",
        "fat": "moderate",
        "salt": "low",
        "saturated_fat": "low",
        "sugars": "low",
        "fat_100g": 6,
        "saturated_fat_100g": 1,
        "sugars_100g": 3,
        "salt_100g": 0
    }
},
{
    "model": "product.product",
    "pk": 75751,
    "fields": {
        "code": "5425008346090",
        "product_name": "P\u00e2te \u00e0 tartiner Noir & Noisette NewTree",
        "brands": "NewTree",
        "categories": "Produits \u00e0 tartiner,Petit-d\u00e9jeuners,Produits \u00e0 tartiner sucr\u00e9s,P\u00e2tes \u00e0 tartiner,P\u00e2tes \u00e0 tartiner au chocolat,P\u00e2tes \u00e0 tartiner aux noisettes,P\u00e2tes \u00e0 tartiner aux noisettes et au cacao",
        "nutrition_grades": "c",
        "url": "https://fr.openfoodfacts.org/produit/5425008346090/pate-a-tartiner-noir-noisette-newtree",
        "image_url": "https://static.openfoodfacts.org/images/products/542/500/834/6090/front_fr.8.400.jpg",
        "image_small_url": "https://static.openfoodfacts.org/images/products/542/500/834/6090/front_fr.8.200.jpg",
        "fat": "moderate",
        "salt": "low",
        "saturated_fat": "moderate",
        "sugars": "high",
        "fat_100g": 16,
        "saturated_fat_100g": 5,
        "sugars_100g": 32,
        "salt_100g": 0
    }
},
{
    "model": "product.product",
    "pk": 68502,
    "fields": {
        "code": "3258590000963",
        "product_name": "P\u00e2te \u00e0 Tartiner Chocolat Noisettes",
        "brands": "Dardenne",
        "categories": "Petit-d\u00e9jeuners,Produits \u00e0 tartiner,Produits \u00e0 tartiner sucr\u00e9s,P\u00e2tes \u00e0 tartiner,P\u00e2tes \u00e0 tartiner au chocolat,P\u00e2tes \u00e0 tartiner aux noisettes,P\u00e2tes \u00e0 tartiner aux noisettes et au cacao",
        "nutrition_grades": "e",
        "url": "https://fr.openfoodfacts.org/produit/3258590000963/pate-a-tartiner-chocolat-noisettes-dardenne",
        "image_url": "https://static.openfoodfacts.org/images/products/325/859/000/0963/front_fr.16.400.jpg",
        "image_small_url": "https://static.openfoodfacts.org/images/products/325/859/000/0963/front_fr.16.200.jpg",
        "fat": "high",
        "salt": "low",
        "saturated_fat": "high",
        "sugars": "high",
        "fat_100g": 36,
        "saturated_fat_100g": 6,
        "sugars_100g": 40,
        "salt_100g": 0
    }
},
{
    "model": "product.product",
    "pk": 62580,
    "fields": {
        "code": "8001505007008",
        "product_name": "Nocciolata",
        "brands": "Rigoni Di Asiago",
        "categories": "Petit-d\u00e9jeuners,Produits \u00e0 tartiner,Produits \u00e0 tartiner sucr\u00e9s,P\u00e2tes \u00e0 tartiner,P\u00e2tes \u00e0 tartiner au chocolat,P\u00e2tes \u00e0 tartiner aux noisettes,P\u00e2tes \u00e0 tartiner aux noisettes et au cacao",
        "nutrition_grades": "d",
        "url": "https://fr.openfoodfacts.org/produit/8001505007008/nocciolata-rigoni-di-asiago",
        "image_url": "https://static.openfoodfacts.org/images/products/800/150/500/7008/front_fr.16.400.jpg",
        "image_small_url": "https://static.openfoodfacts.org/images/products/800/150/500/7008/front_fr.16.200.jpg",
        "fat": "high",
        "salt": "low",
        "saturated_fat": "high",
        "sugars": "high",
        "fat_100g": 30,
        "saturated_fat_100g": 6,
        "sugars_100g": 51,
        "salt_100g": 0
    }
},
{
    "model": "product.product",
    "pk": 36615,
    "fields": {
        "code": "3390390001259",
        "product_name": "P\u00e2te \u00e0 Tartiner Chocolade Sans Lait",
        "brands": "Jean Herv\u00e9",
        "categories": "Petit-d\u00e9jeuners,Produits \u00e0 tartiner,Produits \u00e0 tartiner sucr\u00e9s,P\u00e2tes \u00e0 tartiner,P\u00e2tes \u00e0 tartiner au chocolat,P\u00e2tes \u00e0 tartiner aux noisettes,P\u00e2tes \u00e0 tartiner aux noisettes et au cacao",
        "nutrition_grades": "d",
        "url": "https://fr.openfoodfacts.org/produit/3390390001259/pate-a-tartiner-chocolade-sans-lait-jean-herve",
        "image_url": "https://static.openfoodfacts.org/images/products/339/039/000/1259/front_fr.7.400.jpg",
        "image_small_url": "https://static.openfoodfacts.org/images/products/339/039/000/1259/front_fr.7.200.jpg",
        "fat": "high",
        "salt": "low",
        "saturated_fat": "high",
        "sugars": "high",
        "fat_100g": 45,
        "saturated_fat_100g": 8,
        "sugars_100g": 28,
        "salt_100g": 0
    }
},
{
    "model": "product.product",
    "pk": 35502,
    "fields": {
        "code": "5400141251876",
        "product_name": "P\u00e2te \u00e0 Tartiner Duo aux Noisettes",
        "brands": "Boni",
        "categories": "Produits \u00e0 tartiner,Petit-d\u00e9jeuners,Produits \u00e0 tartiner sucr\u00e9s,P\u00e2tes \u00e0 tartiner,P\u00e2tes \u00e0 tartiner au chocolat,P\u00e2tes \u00e0 tartiner aux noisettes,P\u00e2tes \u00e0 tartiner aux noisettes et au cacao",
        "nutrition_grades": "e",
        "url": "https://fr.openfoodfacts.org/produit/5400141251876/pate-a-tartiner-duo-aux-noisettes-boni",
        "image_url": "https://static.openfoodfacts.org/images/products/540/014/125/1876/front_fr.9.400.jpg",
        "image_small_url": "https://static.openfoodfacts.org/images/products/540/014/125/1876/front_fr.9.200.jpg",
        "fat": "high",
        "salt": "low",
        "saturated_fat": "high",
        "sugars": "high",
        "fat_100g": 35,
        "saturated_fat_100g": 8,
        "sugars_100g": 60,
        "salt_100g": 0
    }
},
{
    "model": "product.product",
    "pk": 35020,
    "fields": {
        "code": "3263852232716",
        "product_name": "P\u00e2te \u00e0 tartiner noisettes",
        "brands": "Franprix",
        "categories": "Petit-d\u00e9jeuners,Produits \u00e0 tartiner,Produits \u00e0 tartiner sucr\u00e9s,P\u00e2tes \u00e0 tartiner,P\u00e2tes \u00e0 tartiner au chocolat,P\u00e2tes \u00e0 tartiner aux noisettes,P\u00e2tes \u00e0 tartiner aux noisettes et au cacao",
        "nutrition_grades": "d",
        "url": "https://fr.openfoodfacts.org/produit/3263852232716/pate-a-tartiner-noisettes-franprix",
        "image_url": "https://static.openfoodfacts.org/images/products/326/385/223/2716/front_fr.7.400.jpg",
        "image_small_url": "https://static.openfoodfacts.org/images/products/326/385/223/2716/front_fr.7.200.jpg",
        "fat": "high",
        "salt": "low",
        "saturated_fat": "high",
        "sugars": "high",
        "fat_100g": 31,
        "saturated_fat_100g": 6,
        "sugars_100g": 55,
        "salt_100g": 0
    }
},
{
    "model": "product.product",
    "pk": 29951,
    "fields": {
        "code": "3596710403721",
        "product_name": "P\u00e2te \u00e0 tartiner aux noisettes et au lait \u00e9cr\u00e9m\u00e9",
        "brands": "Auchan",
        "categories": "Petit-d\u00e9jeuners,Produits \u00e0 tartiner,Produits \u00e0 tartiner sucr\u00e9s,P\u00e2tes \u00e0 tartiner,P\u00e2tes \u00e0 tartiner au chocolat,P\u00e2tes \u00e0 tartiner aux noisettes,P\u00e2tes \u00e0 tartiner aux noisettes et au cacao",
        "nutrition_grades": "e",
        "url": "https://fr.openfoodfacts.org/produit/3596710403721/pate-a-tartiner-aux-noisettes-et-au-lait-ecreme-auchan",
        "image_url": "https://static.openfoodfacts.org/images/products/359/671/040/3721/front_fr.5.400.jpg",
        "image_small_url": "https://static.openfoodfacts.org/images/products/359/671/040/3721/front_fr.5.200.jpg",
        "fat": "high",
        "salt": "low",
        "saturated_fat": "high",
        "sugars": "high",
        "fat_100g": 31,
        "saturated_fat_100g": 6,
        "sugars_100g": 55,
        "salt_100g": 0
    }
},
{
    "model": "product.product",
    "pk": 29950,
    "fields": {
        "code": "3250390860563",
        "product_name": "P\u00e2te \u00e0 Tartiner Duo",
        "brands": "Netto",
        "categories": "Petit-d\u00e9jeuners,Produits \u00e0 tartiner,Produits \u00e0 tartiner sucr\u00e9s,P\u00e2tes \u00e0 tartiner,P\u00e2tes \u00e0 tartiner au chocolat,P\u00e2tes \u00e0 tartiner aux noisettes,P\u00e2tes \u00e0 tartiner aux noisettes et au cacao",
        "nutrition_grades": "e",
        "url": "https://fr.openfoodfacts.org/produit/3250390860563/pate-a-tartiner-duo-netto",
        "image_url": "https://static.openfoodfacts.org/images/products/325/039/086/0563/front_fr.7.400.jpg",
        "image_small_url": "https://static.openfoodfacts.org/images/products/325/039/086/0563/front_fr.7.200.jpg",
        "fat": "high",
        "salt": "low",
        "saturated_fat": "high",
        "sugars": "high",
        "fat_100g": 29,
        "saturated_fat_100g": 11,
        "sugars_100g": 60,
        "salt_100g": 0
    }
},
{
    "model": "product.product",
    "pk": 29949,
    "fields": {
        "code": "3175681105393",
        "product_name": "P\u00e2te \u00e0 tartiner",
        "brands": "Gerbl\u00e9,Glucoregul",
        "categories": "Petit-d\u00e9jeuners,Produits \u00e0 tartiner,Produits \u00e0 tartiner sucr\u00e9s,P\u00e2tes \u00e0 tartiner,P\u00e2tes \u00e0 tartiner au chocolat,P\u00e2tes \u00e0 tartiner aux noisettes,P\u00e2tes \u00e0 tartiner aux noisettes et au cacao",
        "nutrition_grades": "a",
        "url": "https://fr.openfoodfacts.org/produit/3175681105393/pate-a-tartiner-gerble",
        "image_url": "https://static.openfoodfacts.org/images/products/317/568/110/5393/front_fr.11.400.jpg",
        "image_small_url": "https://static.openfoodfacts.org/images/products/317/568/110/5393/front_fr.11.200.jpg",
        "fat": "moderate",
        "salt": "low",
        "saturated_fat": "low",
        "sugars": "moderate",
        "fat_100g": 7,
        "saturated_fat_100g": 1,
        "sugars_100g": 6,
        "salt_100g": 0
    }
},
{
    "model": "product.product",
    "pk": 29948,
    "fields": {
        "code": "3560070167135",
        "product_name": "P\u00e2tes \u00e0 tartiner",
        "brands": "Carrefour",
        "categories": "Petit-d\u00e9jeuners,Produits \u00e0 tartiner,Produits \u00e0 tartiner sucr\u00e9s,P\u00e2tes \u00e0 tartiner,P\u00e2tes \u00e0 tartiner au chocolat,P\u00e2tes \u00e0 tartiner aux noisettes,P\u00e2tes \u00e0 tartiner aux noisettes et au cacao",
        "nutrition_grades": "e",
        "url": "https://fr.openfoodfacts.org/produit/3560070167135/pates-a-tartiner-carrefour",
        "image_url": "https://static.openfoodfacts.org/images/products/356/007/016/7135/front_fr.4.400.jpg",
        "image_small_url": "https://static.openfoodfacts.org/images/products/356/007/016/7135/front_fr.4.200.jpg",
        "fat": "high",
        "salt": "low",
        "saturated_fat": "high",
        "sugars": "high",
        "fat_100g": 29,
        "saturated_fat_100g": 10,
        "sugars_100g": 57,
        "salt_100g": 0
    }
},
{
    "model": "product.product",
    "pk": 29946,
    "fields": {
        "code": "3330720237248",
        "product_name": "Pate \u00e0 tartiner noisette cacao",
        "brands": "Lucien Georgelin",
        "categories": "Petit-d\u00e9jeuners,Produits \u00e0 tartiner,Produits \u00e0 tartiner sucr\u00e9s,P\u00e2tes \u00e0 tartiner,P\u00e2tes \u00e0 tartiner au chocolat,P\u00e2tes \u00e0 tartiner aux noisettes,P\u00e2tes \u00e0 tartiner aux noisettes et au cacao",
        "nutrition_grades": "e",
        "url": "https://fr.openfoodfacts.org/produit/3330720237248/pate-a-tartiner-noisette-cacao-lucien-georgelin",
        "image_url": "https://static.openfoodfacts.org/images/products/333/072/023/7248/front_fr.12.400.jpg",
        "image_small_url": "https://static.openfoodfacts.org/images/products/333/072/023/7248/front_fr.12.200.jpg",
        "fat": "high",
        "salt": "low",
        "saturated_fat": "high",
        "sugars": "high",
        "fat_100g": 31,
        "saturated_fat_100g": 7,
        "sugars_100g": 50,
        "salt_100g": 0
    }
},
{
    "model": "product.product",
    "pk": 29939,
    "fields": {
        "code": "3410280023229",
        "product_name": "P\u00e2te \u00e0 tartiner aux noisettes et au cacao",
        "brands": "Top Budget",
        "categories": "Petit-d\u00e9jeuners,Produits \u00e0 tartiner,Produits \u00e0 tartiner sucr\u00e9s,P\u00e2tes \u00e0 tartiner,P\u00e2tes \u00e0 tartiner au chocolat,P\u00e2tes \u00e0 tartiner aux noisettes,P\u00e2tes \u00e0 tartiner aux noisettes et au cacao",
        "nutrition_grades": "e",
        "url": "https://fr.openfoodfacts.org/produit/3410280023229/pate-a-tartiner-aux-noisettes-et-au-cacao-top-budget",
        "image_url": "https://static.openfoodfacts.org/images/products/341/028/002/3229/front_fr.6.400.jpg",
        "image_small_url": "https://static.openfoodfacts.org/images/products/341/028/002/3229/front_fr.6.200.jpg",
        "fat": "high",
        "salt": "low",
        "saturated_fat": "high",
        "sugars": "high",
        "fat_100g": 32,
        "saturated_fat_100g": 14,
        "sugars_100g": 55,
        "salt_100g": 0
    }
},
{
    "model": "product.product",
    "pk": 29937,
    "fields": {
        "code": "3257984362861",
        "product_name": "p\u00e2te \u00e0 Tartiner",
        "brands": "Cora",
        "categories": "Petit-d\u00e9jeuners,Produits \u00e0 tartiner,Produits \u00e0 tartiner sucr\u00e9s,P\u00e2tes \u00e0 tartiner,P\u00e2tes \u00e0 tartiner au chocolat,P\u00e2tes \u00e0 tartiner aux noisettes,P\u00e2tes \u00e0 tartiner aux noisettes et au cacao",
        "nutrition_grades": "d",
        "url": "https://fr.openfoodfacts.org/produit/3257984362861/pate-a-tartiner-cora",
        "image_url": "https://static.openfoodfacts.org/images/products/325/798/436/2861/front_fr.8.400.jpg",
        "image_small_url": "https://static.openfoodfacts.org/images/products/325/798/436/2861/front_fr.8.200.jpg",
        "fat": "high",
        "salt": "low",
        "saturated_fat": "high",
        "sugars": "high",
        "fat_100g": 31,
        "saturated_fat_100g": 6,
        "sugars_100g": 55,
        "salt_100g": 0
    }
},
{
    "model": "product.product",
    "pk": 29935,
    "fields": {
        "code": "3266191006864",
        "product_name": "P\u00e2te \u00e0 tartiner Noisette Cacao",
        "brands": "La Vie Claire",
        "categories": "Petit-d\u00e9jeuners,Produits \u00e0 tartiner,Produits \u00e0 tartiner sucr\u00e9s,P\u00e2tes \u00e0 tartiner,P\u00e2tes \u00e0 tartiner au chocolat,P\u00e2tes \u00e0 tartiner aux noisettes,P\u00e2tes \u00e0 tartiner aux noisettes et au cacao",
        "nutrition_grades": "d",
        "url": "https://fr.openfoodfacts.org/produit/3266191006864/pate-a-tartiner-noisette-cacao-la-vie-claire",
        "image_url": "https://static.openfoodfacts.org/images/products/326/619/100/6864/front_fr.5.400.jpg",
        "image_small_url": "https://static.openfoodfacts.org/images/products/326/619/100/6864/front_fr.5.200.jpg",
        "fat": "high",
        "salt": "low",
        "saturated_fat": "moderate",
        "sugars": "high",
        "fat_100g": 35,
        "saturated_fat_100g": 5,
        "sugars_100g": 53,
        "salt_100g": 0
    }
},
{
    "model": "product.product",
    "pk": 29934,
    "fields": {
        "code": "3390390001648",
        "product_name": "P\u00e2te \u00e0 tartiner noisette-cacao",
        "brands": "Ti Bio",
        "categories": "Petit-d\u00e9jeuners,Produits \u00e0 tartiner,Produits \u00e0 tartiner sucr\u00e9s,P\u00e2tes \u00e0 tartiner,P\u00e2tes \u00e0 tartiner au chocolat,P\u00e2tes \u00e0 tartiner aux noisettes,P\u00e2tes \u00e0 tartiner aux noisettes et au cacao",
        "nutrition_grades": "e",
        "url": "https://fr.openfoodfacts.org/produit/3390390001648/pate-a-tartiner-noisette-cacao-ti-bio",
        "image_url": "https://static.openfoodfacts.org/images/products/339/039/000/1648/front_fr.6.400.jpg",
        "image_small_url": "https://static.openfoodfacts.org/images/products/339/039/000/1648/front_fr.6.200.jpg",
        "fat": "high",
        "salt": "low",
        "saturated_fat": "high",
        "sugars": "high",
        "fat_100g": 41,
        "saturated_fat_100g": 12,
        "sugars_100g": 35,
        "salt_100g": 0
    }
},
{
    "model": "product.product",
    "pk": 29933,
    "fields": {
        "code": "5400141405316",
        "product_name": "P\u00e2te a tartiner aux noisettes duo",
        "brands": "Boni",
        "categories": "Petit-d\u00e9jeuners,Produits \u00e0 tartiner,Produits \u00e0 tartiner sucr\u00e9s,P\u00e2tes \u00e0 tartiner,P\u00e2tes \u00e0 tartiner au chocolat,P\u00e2tes \u00e0 tartiner aux noisettes,P\u00e2tes \u00e0 tartiner aux noisettes et au cacao",
        "nutrition_grades": "e",
        "url": "https://fr.openfoodfacts.org/produit/5400141405316/pate-a-tartiner-aux-noisettes-duo-boni",
        "image_url": "https://static.openfoodfacts.org/images/products/540/014/140/5316/front_fr.6.400.jpg",
        "image_small_url": "https://static.openfoodfacts.org/images/products/540/014/140/5316/front_fr.6.200.jpg",
        "fat": "high",
        "salt": "low",
        "saturated_fat": "high",
        "sugars": "high",
        "fat_100g": 35,
        "saturated_fat_100g": 8,
        "sugars_100g": 60,
        "salt_100g": 0
    }
},
{
    "model": "product.product",
    "pk": 29932,
    "fields": {
        "code": "7350021421425",
        "product_name": "Proteinella Chocolat-Noisettes",
        "brands": "Healthyco",
        "categories": "Petit-d\u00e9jeuners,Produits \u00e0 tartiner,Produits \u00e0 tartiner sucr\u00e9s,P\u00e2tes \u00e0 tartiner,P\u00e2tes \u00e0 tartiner au chocolat,P\u00e2tes \u00e0 tartiner aux noisettes,P\u00e2tes \u00e0 tartiner aux noisettes et au cacao",
        "nutrition_grades": "d",
        "url": "https://fr.openfoodfacts.org/produit/7350021421425/proteinella-chocolat-noisettes-healthyco",
        "image_url": "https://static.openfoodfacts.org/images/products/735/002/142/1425/front_fr.5.400.jpg",
        "image_small_url": "https://static.openfoodfacts.org/images/products/735/002/142/1425/front_fr.5.200.jpg",
        "fat": "high",
        "salt": "low",
        "saturated_fat": "high",
        "sugars": "moderate",
        "fat_100g": 35,
        "saturated_fat_100g": 8,
        "sugars_100g": 7,
        "salt_100g": 0
    }
},
{
    "model": "product.product",
    "pk": 29925,
    "fields": {
        "code": "3662343481013",
        "product_name": "P\u00e2te \u00e0 tartiner noisettes cacao",
        "brands": "La Vie Claire",
        "categories": "Petit-d\u00e9jeuners,Produits \u00e0 tartiner,Produits \u00e0 tartiner sucr\u00e9s,P\u00e2tes \u00e0 tartiner,P\u00e2tes \u00e0 tartiner au chocolat,P\u00e2tes \u00e0 tartiner aux noisettes,P\u00e2tes \u00e0 tartiner aux noisettes et au cacao",
        "nutrition_grades": "d",
        "url": "https://fr.openfoodfacts.org/produit/3662343481013/pate-a-tartiner-noisettes-cacao-la-vie-claire",
        "image_url": "https://static.openfoodfacts.org/images/products/366/234/348/1013/front_fr.12.400.jpg",
        "image_small_url": "https://static.openfoodfacts.org/images/products/366/234/348/1013/front_fr.12.200.jpg",
        "fat": "high",
        "salt": "low",
        "saturated_fat": "moderate",
        "sugars": "high",
        "fat_100g": 35,
        "saturated_fat_100g": 5,
        "sugars_100g": 53,
        "salt_100g": 0
    }
},
{
    "model": "product.product",
    "pk": 29924,
    "fields": {
        "code": "3102621006205",
        "product_name": "P\u00e2te \u00e0 tartiner Chocolat Noir & Noisettes",
        "brands": "Le Roy Ren\u00e9",
        "categories": "Petit-d\u00e9jeuners,Produits \u00e0 tartiner,Produits \u00e0 tartiner sucr\u00e9s,P\u00e2tes \u00e0 tartiner,P\u00e2tes \u00e0 tartiner au chocolat,P\u00e2tes \u00e0 tartiner aux noisettes,P\u00e2tes \u00e0 tartiner aux noisettes et au cacao",
        "nutrition_grades": "d",
        "url": "https://fr.openfoodfacts.org/produit/3102621006205/pate-a-tartiner-chocolat-noir-noisettes-le-roy-rene",
        "image_url": "https://static.openfoodfacts.org/images/products/310/262/100/6205/front_fr.4.400.jpg",
        "image_small_url": "https://static.openfoodfacts.org/images/products/310/262/100/6205/front_fr.4.200.jpg",
        "fat": "high",
        "salt": "low",
        "saturated_fat": "moderate",
        "sugars": "high",
        "fat_100g": 38,
        "saturated_fat_100g": 3,
        "sugars_100g": 41,
        "salt_100g": 0
    }
},
{
    "model": "product.product",
    "pk": 29923,
    "fields": {
        "code": "3501940532004",
        "product_name": "P\u00e2te \u00e0 Tartiner Noisette Chocolat au Lait Caramel et Sel de Gu\u00e9rande",
        "brands": "Bovetti",
        "categories": "Petit-d\u00e9jeuners,Produits \u00e0 tartiner,Produits \u00e0 tartiner sucr\u00e9s,P\u00e2tes \u00e0 tartiner,P\u00e2tes \u00e0 tartiner au chocolat,P\u00e2tes \u00e0 tartiner aux noisettes,P\u00e2tes \u00e0 tartiner aux noisettes et au cacao",
        "nutrition_grades": "e",
        "url": "https://fr.openfoodfacts.org/produit/3501940532004/pate-a-tartiner-noisette-chocolat-au-lait-caramel-et-sel-de-guerande-bovetti",
        "image_url": "https://static.openfoodfacts.org/images/products/350/194/053/2004/front_fr.4.400.jpg",
        "image_small_url": "https://static.openfoodfacts.org/images/products/350/194/053/2004/front_fr.4.200.jpg",
        "fat": "high",
        "salt": "low",
        "saturated_fat": "high",
        "sugars": "high",
        "fat_100g": 49,
        "saturated_fat_100g": 10,
        "sugars_100g": 28,
        "salt_100g": 0
    }
},
{
    "model": "product.product",
    "pk": 29922,
    "fields": {
        "code": "3456300004755",
        "product_name": "P\u00e2te \u00e0 tartiner sans sucres ajout\u00e9s",
        "brands": "Kar\u00e9l\u00e9a",
        "categories": "Petit-d\u00e9jeuners,Produits \u00e0 tartiner,Produits \u00e0 tartiner sucr\u00e9s,P\u00e2tes \u00e0 tartiner,P\u00e2tes \u00e0 tartiner au chocolat,P\u00e2tes \u00e0 tartiner aux noisettes,P\u00e2tes \u00e0 tartiner aux noisettes et au cacao",
        "nutrition_grades": "c",
        "url": "https://fr.openfoodfacts.org/produit/3456300004755/pate-a-tartiner-sans-sucres-ajoutes-karelea",
        "image_url": "https://static.openfoodfacts.org/images/products/345/630/000/4755/front_fr.15.400.jpg",
        "image_small_url": "https://static.openfoodfacts.org/images/products/345/630/000/4755/front_fr.15.200.jpg",
        "fat": "high",
        "salt": "low",
        "saturated_fat": "high",
        "sugars": "moderate",
        "fat_100g": 34,
        "saturated_fat_100g": 7,
        "sugars_100g": 8,
        "salt_100g": 0
    }
},
{
    "model": "product.product",
    "pk": 29921,
    "fields": {
        "code": "3596710176205",
        "product_name": "P\u00e2te \u00e0 Tartiner aux Noisettes",
        "brands": "Auchan Pouce,Pouce,Auchan",
        "categories": "Petit-d\u00e9jeuners,Produits \u00e0 tartiner,Produits \u00e0 tartiner sucr\u00e9s,P\u00e2tes \u00e0 tartiner,P\u00e2tes \u00e0 tartiner au chocolat,P\u00e2tes \u00e0 tartiner aux noisettes,P\u00e2tes \u00e0 tartiner aux noisettes et au cacao",
        "nutrition_grades": "e",
        "url": "https://fr.openfoodfacts.org/produit/3596710176205/pate-a-tartiner-aux-noisettes-auchan-pouce",
        "image_url": "https://static.openfoodfacts.org/images/products/359/671/017/6205/front_fr.8.400.jpg",
        "image_small_url": "https://static.openfoodfacts.org/images/products/359/671/017/6205/front_fr.8.200.jpg",
        "fat": "high",
        "salt": "low",
        "saturated_fat": "high",
        "sugars": "high",
        "fat_100g": 31,
        "saturated_fat_100g": 7,
        "sugars_100g": 57,
        "salt_100g": 0
    }
},
{
    "model": "product.product",
    "pk": 25511,
    "fields": {
        "code": "3760076001345",
        "product_name": "P\u00e2te \u00e0 tartiner Chok\u00e9nut",
        "brands": "Chokenut",
        "categories": "Petit-d\u00e9jeuners,Produits \u00e0 tartiner,Produits \u00e0 tartiner sucr\u00e9s,P\u00e2tes \u00e0 tartiner,P\u00e2tes \u00e0 tartiner au chocolat,P\u00e2tes \u00e0 tartiner aux noisettes,P\u00e2tes \u00e0 tartiner aux noisettes et au cacao",
        "nutrition_grades": "e",
        "url": "https://fr.openfoodfacts.org/produit/3760076001345/pate-a-tartiner-chokenut",
        "image_url": "https://static.openfoodfacts.org/images/products/376/007/600/1345/front_fr.17.400.jpg",
        "image_small_url": "https://static.openfoodfacts.org/images/products/376/007/600/1345/front_fr.17.200.jpg",
        "fat": "high",
        "salt": "low",
        "saturated_fat": "high",
        "sugars": "high",
        "fat_100g": 47,
        "saturated_fat_100g": 16,
        "sugars_100g": 39,
        "salt_100g": 0
    }
},
{
    "model": "product.product",
    "pk": 22614,
    "fields": {
        "code": "3596710427734",
        "product_name": "P\u00e2te \u00e0 tartiner aux noisettes et au lait \u00e9cr\u00e9m\u00e9",
        "brands": "Auchan",
        "categories": "Petit-d\u00e9jeuners,Produits \u00e0 tartiner,Produits \u00e0 tartiner sucr\u00e9s,P\u00e2tes \u00e0 tartiner,P\u00e2tes \u00e0 tartiner au chocolat,P\u00e2tes \u00e0 tartiner aux noisettes,P\u00e2tes \u00e0 tartiner aux noisettes et au cacao",
        "nutrition_grades": "d",
        "url": "https://fr.openfoodfacts.org/produit/3596710427734/pate-a-tartiner-aux-noisettes-et-au-lait-ecreme-auchan",
        "image_url": "https://static.openfoodfacts.org/images/products/359/671/042/7734/front_fr.8.400.jpg",
        "image_small_url": "https://static.openfoodfacts.org/images/products/359/671/042/7734/front_fr.8.200.jpg",
        "fat": "high",
        "salt": "low",
        "saturated_fat": "high",
        "sugars": "high",
        "fat_100g": 31,
        "saturated_fat_100g": 6,
        "sugars_100g": 55,
        "salt_100g": 0
    }
},
{
    "model": "product.product",
    "pk": 22553,
    "fields": {
        "code": "3760076001512",
        "product_name": "NUTE +",
        "brands": "Nut\u00e9+",
        "categories": "Petit-d\u00e9jeuners,Produits \u00e0 tartiner,Produits \u00e0 tartiner sucr\u00e9s,P\u00e2tes \u00e0 tartiner,P\u00e2tes \u00e0 tartiner au chocolat,P\u00e2tes \u00e0 tartiner aux noisettes,P\u00e2tes \u00e0 tartiner aux noisettes et au cacao",
        "nutrition_grades": "e",
        "url": "https://fr.openfoodfacts.org/produit/3760076001512/nute",
        "image_url": "https://static.openfoodfacts.org/images/products/376/007/600/1512/front_fr.10.400.jpg",
        "image_small_url": "https://static.openfoodfacts.org/images/products/376/007/600/1512/front_fr.10.200.jpg",
        "fat": "high",
        "salt": "low",
        "saturated_fat": "high",
        "sugars": "high",
        "fat_100g": 36,
        "saturated_fat_100g": 19,
        "sugars_100g": 37,
        "salt_100g": 0
    }
},
{
    "model": "product.product",
    "pk": 22359,
    "fields": {
        "code": "8001505005592",
        "product_name": "Nocciolata P\u00e2te \u00e0 tartiner au cacao et noisettes",
        "brands": "Rigoni di Asiago",
        "categories": "Petit-d\u00e9jeuners,Produits \u00e0 tartiner,Produits \u00e0 tartiner sucr\u00e9s,P\u00e2tes \u00e0 tartiner,P\u00e2tes \u00e0 tartiner au chocolat,P\u00e2tes \u00e0 tartiner aux noisettes,P\u00e2tes \u00e0 tartiner aux noisettes et au cacao",
        "nutrition_grades": "d",
        "url": "https://fr.openfoodfacts.org/produit/8001505005592/nocciolata-pate-a-tartiner-au-cacao-et-noisettes-rigoni-di-asiago",
        "image_url": "https://static.openfoodfacts.org/images/products/800/150/500/5592/front_fr.39.400.jpg",
        "image_small_url": "https://static.openfoodfacts.org/images/products/800/150/500/5592/front_fr.39.200.jpg",
        "fat": "high",
        "salt": "low",
        "saturated_fat": "high",
        "sugars": "high",
        "fat_100g": 30,
        "saturated_fat_100g": 6,
        "sugars_100g": 51,
        "salt_100g": 0
    }
},
{
    "model": "product.product",
    "pk": 22004,
    "fields": {
        "code": "3229820189512",
        "product_name": "Cacao Noisette A Tartiner",
        "brands": "Bjorg",
        "categories": "Petit-d\u00e9jeuners,Produits \u00e0 tartiner,Produits \u00e0 tartiner sucr\u00e9s,P\u00e2tes \u00e0 tartiner,P\u00e2tes \u00e0 tartiner au chocolat,P\u00e2tes \u00e0 tartiner aux noisettes,P\u00e2tes \u00e0 tartiner aux noisettes et au cacao",
        "nutrition_grades": "e",
        "url": "https://fr.openfoodfacts.org/produit/3229820189512/cacao-noisette-a-tartiner-bjorg",
        "image_url": "https://static.openfoodfacts.org/images/products/322/982/018/9512/front_fr.8.400.jpg",
        "image_small_url": "https://static.openfoodfacts.org/images/products/322/982/018/9512/front_fr.8.200.jpg",
        "fat": "high",
        "salt": "high",
        "saturated_fat": "high",
        "sugars": "high",
        "fat_100g": 36,
        "saturated_fat_100g": 7,
        "sugars_100g": 40,
        "salt_100g": 2
    }
},
{
    "model": "product.product",
    "pk": 20052,
    "fields": {
        "code": "3350033298453",
        "product_name": "P\u00e2te \u00e0 Tartiner Noisettes",
        "brands": "Monoprix P'tit Prix,Monoprix",
        "categories": "Produits \u00e0 tartiner,Petit-d\u00e9jeuners,Produits \u00e0 tartiner sucr\u00e9s,P\u00e2tes \u00e0 tartiner,P\u00e2tes \u00e0 tartiner au chocolat,P\u00e2tes \u00e0 tartiner aux noisettes,P\u00e2tes \u00e0 tartiner aux noisettes et au cacao",
        "nutrition_grades": "d",
        "url": "https://fr.openfoodfacts.org/produit/3350033298453/pate-a-tartiner-noisettes-monoprix-p-tit-prix",
        "image_url": "https://static.openfoodfacts.org/images/products/335/003/329/8453/front_fr.3.400.jpg",
        "image_small_url": "https://static.openfoodfacts.org/images/products/335/003/329/8453/front_fr.3.200.jpg",
        "fat": "high",
        "salt": "low",
        "saturated_fat": "high",
        "sugars": "high",
        "fat_100g": 31,
        "saturated_fat_100g": 6,
        "sugars_100g": 55,
        "salt_100g": 0
    }
},
{
    "model": "product.product",
    "pk": 20043,
    "fields": {
        "code": "3250390114161",
        "product_name": "Noikao",
        "brands": "Ivoria",
        "categories": "Petit-d\u00e9jeuners,Produits \u00e0 tartiner,Produits \u00e0 tartiner sucr\u00e9s,P\u00e2tes \u00e0 tartiner,P\u00e2tes \u00e0 tartiner au chocolat,P\u00e2tes \u00e0 tartiner aux noisettes,P\u00e2tes \u00e0 tartiner aux noisettes et au cacao",
        "nutrition_grades": "e",
        "url": "https://fr.openfoodfacts.org/produit/3250390114161/noikao-ivoria",
        "image_url": "https://static.openfoodfacts.org/images/products/325/039/011/4161/front_fr.6.400.jpg",
        "image_small_url": "https://static.openfoodfacts.org/images/products/325/039/011/4161/front_fr.6.200.jpg",
        "fat": "high",
        "salt": "low",
        "saturated_fat": "high",
        "sugars": "high",
        "fat_100g": 30,
        "saturated_fat_100g": 10,
        "sugars_100g": 59,
        "salt_100g": 0
    }
},
{
    "model": "product.product",
    "pk": 19997,
    "fields": {
        "code": "3760091727084",
        "product_name": "P\u00e2te \u00e0 tartiner aux Noisettes",
        "brands": "Ethiquable",
        "categories": "Petit-d\u00e9jeuners,Produits \u00e0 tartiner,Produits \u00e0 tartiner sucr\u00e9s,P\u00e2tes \u00e0 tartiner,P\u00e2tes \u00e0 tartiner au chocolat,P\u00e2tes \u00e0 tartiner aux noisettes,P\u00e2tes \u00e0 tartiner aux noisettes et au cacao",
        "nutrition_grades": "e",
        "url": "https://fr.openfoodfacts.org/produit/3760091727084/pate-a-tartiner-aux-noisettes-ethiquable",
        "image_url": "https://static.openfoodfacts.org/images/products/376/009/172/7084/front_fr.10.400.jpg",
        "image_small_url": "https://static.openfoodfacts.org/images/products/376/009/172/7084/front_fr.10.200.jpg",
        "fat": "high",
        "salt": "low",
        "saturated_fat": "high",
        "sugars": "high",
        "fat_100g": 42,
        "saturated_fat_100g": 11,
        "sugars_100g": 43,
        "salt_100g": 0
    }
},
{
    "model": "product.product",
    "pk": 19319,
    "fields": {
        "code": "3248652786133",
        "product_name": "Pate a tartiner",
        "brands": "Monoprix",
        "categories": "P\u00e2tes \u00e0 tartiner,P\u00e2tes \u00e0 tartiner au chocolat,P\u00e2tes \u00e0 tartiner aux noisettes,P\u00e2tes \u00e0 tartiner aux noisettes et au cacao",
        "nutrition_grades": "d",
        "url": "https://fr.openfoodfacts.org/produit/3248652786133/pate-a-tartiner-monoprix",
        "image_url": "https://static.openfoodfacts.org/images/products/324/865/278/6133/front_fr.30.400.jpg",
        "image_small_url": "https://static.openfoodfacts.org/images/products/324/865/278/6133/front_fr.30.200.jpg",
        "fat": "high",
        "salt": "low",
        "saturated_fat": "high",
        "sugars": "high",
        "fat_100g": 31,
        "saturated_fat_100g": 6,
        "sugars_100g": 55,
        "salt_100g": 0
    }
},
{
    "model": "product.product",
    "pk": 17777,
    "fields": {
        "code": "8025128009157",
        "product_name": "Equobonita Classic",
        "brands": "Liberomondo",
        "categories": "Petit-d\u00e9jeuners,Produits \u00e0 tartiner,Produits \u00e0 tartiner sucr\u00e9s,P\u00e2tes \u00e0 tartiner,P\u00e2tes \u00e0 tartiner au chocolat,P\u00e2tes \u00e0 tartiner aux noisettes,P\u00e2tes \u00e0 tartiner aux noisettes et au cacao",
        "nutrition_grades": "e",
        "url": "https://fr.openfoodfacts.org/produit/8025128009157/equobonita-classic-liberomondo",
        "image_url": "https://static.openfoodfacts.org/images/products/802/512/800/9157/front_fr.4.400.jpg",
        "image_small_url": "https://static.openfoodfacts.org/images/products/802/512/800/9157/front_fr.4.200.jpg",
        "fat": "high",
        "salt": "low",
        "saturated_fat": "high",
        "sugars": "high",
        "fat_100g": 30,
        "saturated_fat_100g": 6,
        "sugars_100g": 56,
        "salt_100g": 0
    }
},
{
    "model": "product.product",
    "pk": 17045,
    "fields": {
        "code": "3760076001543",
        "product_name": "P\u00e2te \u00e0 Tartiner sans lait Chocolinette",
        "brands": "Noiseraie,Chocolinette",
        "categories": "Petit-d\u00e9jeuners,Produits \u00e0 tartiner,Produits \u00e0 tartiner sucr\u00e9s,P\u00e2tes \u00e0 tartiner,P\u00e2tes \u00e0 tartiner au chocolat,P\u00e2tes \u00e0 tartiner aux noisettes,P\u00e2tes \u00e0 tartiner aux noisettes et au cacao",
        "nutrition_grades": "e",
        "url": "https://fr.openfoodfacts.org/produit/3760076001543/pate-a-tartiner-sans-lait-chocolinette-noiseraie",
        "image_url": "https://static.openfoodfacts.org/images/products/376/007/600/1543/front_fr.19.400.jpg",
        "image_small_url": "https://static.openfoodfacts.org/images/products/376/007/600/1543/front_fr.19.200.jpg",
        "fat": "high",
        "salt": "low",
        "saturated_fat": "high",
        "sugars": "high",
        "fat_100g": 45,
        "saturated_fat_100g": 17,
        "sugars_100g": 39,
        "salt_100g": 0
    }
},
{
    "model": "product.product",
    "pk": 16828,
    "fields": {
        "code": "3421371518609",
        "product_name": "P\u00e2te \u00e0 tartiner",
        "brands": "Chevaliers d'Argouges",
        "categories": "Petit-d\u00e9jeuners,Produits \u00e0 tartiner,Produits \u00e0 tartiner sucr\u00e9s,P\u00e2tes \u00e0 tartiner,P\u00e2tes \u00e0 tartiner au chocolat,P\u00e2tes \u00e0 tartiner aux noisettes,P\u00e2tes \u00e0 tartiner aux noisettes et au cacao",
        "nutrition_grades": "e",
        "url": "https://fr.openfoodfacts.org/produit/3421371518609/pate-a-tartiner-chevaliers-d-argouges",
        "image_url": "https://static.openfoodfacts.org/images/products/342/137/151/8609/front_fr.17.400.jpg",
        "image_small_url": "https://static.openfoodfacts.org/images/products/342/137/151/8609/front_fr.17.200.jpg",
        "fat": "high",
        "salt": "low",
        "saturated_fat": "high",
        "sugars": "high",
        "fat_100g": 31,
        "saturated_fat_100g": 7,
        "sugars_100g": 50,
        "salt_100g": 0
    }
},
{
    "model": "product.product",
    "pk": 16826,
    "fields": {
        "code": "3257984627328",
        "product_name": "P\u00e2te \u00e0 tartiner",
        "brands": "Cora",
        "categories": "Petit-d\u00e9jeuners,Produits \u00e0 tartiner,Produits \u00e0 tartiner sucr\u00e9s,P\u00e2tes \u00e0 tartiner,P\u00e2tes \u00e0 tartiner au chocolat,P\u00e2tes \u00e0 tartiner aux noisettes,P\u00e2tes \u00e0 tartiner aux noisettes et au cacao",
        "nutrition_grades": "d",
        "url": "https://fr.openfoodfacts.org/produit/3257984627328/pate-a-tartiner-cora",
        "image_url": "https://static.openfoodfacts.org/images/products/325/798/462/7328/front_fr.20.400.jpg",
        "image_small_url": "https://static.openfoodfacts.org/images/products/325/798/462/7328/front_fr.20.200.jpg",
        "fat": "high",
        "salt": "low",
        "saturated_fat": "high",
        "sugars": "high",
        "fat_100g": 31,
        "saturated_fat_100g": 6,
        "sugars_100g": 55,
        "salt_100g": 0
    }
},
{
    "model": "product.product",
    "pk": 16823,
    "fields": {
        "code": "3250392396992",
        "product_name": "J'adore la p\u00e2te \u00e0 tartiner sans huile de palme",
        "brands": "Ivoria",
        "categories": "Petit-d\u00e9jeuners,Produits \u00e0 tartiner,Produits \u00e0 tartiner sucr\u00e9s,P\u00e2tes \u00e0 tartiner,P\u00e2tes \u00e0 tartiner au chocolat,P\u00e2tes \u00e0 tartiner aux noisettes,P\u00e2tes \u00e0 tartiner aux noisettes et au cacao",
        "nutrition_grades": "e",
        "url": "https://fr.openfoodfacts.org/produit/3250392396992/j-adore-la-pate-a-tartiner-sans-huile-de-palme-ivoria",
        "image_url": "https://static.openfoodfacts.org/images/products/325/039/239/6992/front_fr.8.400.jpg",
        "image_small_url": "https://static.openfoodfacts.org/images/products/325/039/239/6992/front_fr.8.200.jpg",
        "fat": "high",
        "salt": "low",
        "saturated_fat": "high",
        "sugars": "high",
        "fat_100g": 32,
        "saturated_fat_100g": 6,
        "sugars_100g": 54,
        "salt_100g": 0
    }
},
{
    "model": "product.product",
    "pk": 16817,
    "fields": {
        "code": "3266191006871",
        "product_name": "P\u00e2te A Tartiner Noisette Cacao",
        "brands": "La Vie Claire",
        "categories": "Petit-d\u00e9jeuners,Produits \u00e0 tartiner,Produits \u00e0 tartiner sucr\u00e9s,P\u00e2tes \u00e0 tartiner,P\u00e2tes \u00e0 tartiner au chocolat,P\u00e2tes \u00e0 tartiner aux noisettes,P\u00e2tes \u00e0 tartiner aux noisettes et au cacao",
        "nutrition_grades": "d",
        "url": "https://fr.openfoodfacts.org/produit/3266191006871/pate-a-tartiner-noisette-cacao-la-vie-claire",
        "image_url": "https://static.openfoodfacts.org/images/products/326/619/100/6871/front_fr.18.400.jpg",
        "image_small_url": "https://static.openfoodfacts.org/images/products/326/619/100/6871/front_fr.18.200.jpg",
        "fat": "high",
        "salt": "low",
        "saturated_fat": "moderate",
        "sugars": "high",
        "fat_100g": 35,
        "saturated_fat_100g": 5,
        "sugars_100g": 53,
        "salt_100g": 0
    }
},
{
    "model": "product.product",
    "pk": 16815,
    "fields": {
        "code": "8001505000658",
        "product_name": "Nocciolata sans lait",
        "brands": "Rigoni Di Asiago",
        "categories": "Petit-d\u00e9jeuners,Produits \u00e0 tartiner,Produits \u00e0 tartiner sucr\u00e9s,P\u00e2tes \u00e0 tartiner,P\u00e2tes \u00e0 tartiner au chocolat,P\u00e2tes \u00e0 tartiner aux noisettes,P\u00e2tes \u00e0 tartiner aux noisettes et au cacao",
        "nutrition_grades": "d",
        "url": "https://fr.openfoodfacts.org/produit/8001505000658/nocciolata-sans-lait-rigoni-di-asiago",
        "image_url": "https://static.openfoodfacts.org/images/products/800/150/500/0658/front_fr.12.400.jpg",
        "image_small_url": "https://static.openfoodfacts.org/images/products/800/150/500/0658/front_fr.12.200.jpg",
        "fat": "high",
        "salt": "low",
        "saturated_fat": "high",
        "sugars": "high",
        "fat_100g": 31,
        "saturated_fat_100g": 5,
        "sugars_100g": 50,
        "salt_100g": 0
    }
},
{
    "model": "product.product",
    "pk": 16814,
    "fields": {
        "code": "8001505004359",
        "product_name": "Nocciolaia Rigoni",
        "brands": "Rigoni Di Asiago",
        "categories": "Petit-d\u00e9jeuners,Produits \u00e0 tartiner,Produits \u00e0 tartiner sucr\u00e9s,P\u00e2tes \u00e0 tartiner,P\u00e2tes \u00e0 tartiner au chocolat,P\u00e2tes \u00e0 tartiner aux noisettes,P\u00e2tes \u00e0 tartiner aux noisettes et au cacao,Crema spalmabile alle nocciole",
        "nutrition_grades": "d",
        "url": "https://fr.openfoodfacts.org/produit/8001505004359/nocciolaia-rigoni-rigoni-di-asiago",
        "image_url": "https://static.openfoodfacts.org/images/products/800/150/500/4359/front_fr.6.400.jpg",
        "image_small_url": "https://static.openfoodfacts.org/images/products/800/150/500/4359/front_fr.6.200.jpg",
        "fat": "high",
        "salt": "low",
        "saturated_fat": "high",
        "sugars": "high",
        "fat_100g": 30,
        "saturated_fat_100g": 6,
        "sugars_100g": 51,
        "salt_100g": 0
    }
},
{
    "model": "product.product",
    "pk": 16813,
    "fields": {
        "code": "7610848654681",
        "product_name": "P\u00e2te \u00e0 Tartiner Aux Noisettes",
        "brands": "Coop,Coop Qualit\u00e9 & Prix",
        "categories": "Petit-d\u00e9jeuners,Produits \u00e0 tartiner,Produits \u00e0 tartiner sucr\u00e9s,P\u00e2tes \u00e0 tartiner,P\u00e2tes \u00e0 tartiner au chocolat,P\u00e2tes \u00e0 tartiner aux noisettes,P\u00e2tes \u00e0 tartiner aux noisettes et au cacao",
        "nutrition_grades": "e",
        "url": "https://fr.openfoodfacts.org/produit/7610848654681/pate-a-tartiner-aux-noisettes-coop",
        "image_url": "https://static.openfoodfacts.org/images/products/761/084/865/4681/front_fr.24.400.jpg",
        "image_small_url": "https://static.openfoodfacts.org/images/products/761/084/865/4681/front_fr.24.200.jpg",
        "fat": "high",
        "salt": "low",
        "saturated_fat": "high",
        "sugars": "high",
        "fat_100g": 29,
        "saturated_fat_100g": 10,
        "sugars_100g": 57,
        "salt_100g": 0
    }
},
{
    "model": "product.product",
    "pk": 16811,
    "fields": {
        "code": "3760072010204",
        "product_name": "P\u00e2te \u00e0 Tartiner Ch\u00e2taigne Chocolat Noisette",
        "brands": "G.A.E.C. Marron Ch\u00e2taigne,Marron Ch\u00e2taigne",
        "categories": "Petit-d\u00e9jeuners,Produits \u00e0 tartiner,Produits \u00e0 tartiner sucr\u00e9s,P\u00e2tes \u00e0 tartiner,P\u00e2tes \u00e0 tartiner au chocolat,P\u00e2tes \u00e0 tartiner aux noisettes,P\u00e2tes \u00e0 tartiner aux noisettes et au cacao",
        "nutrition_grades": "d",
        "url": "https://fr.openfoodfacts.org/produit/3760072010204/pate-a-tartiner-chataigne-chocolat-noisette-g-a-e-c-marron-chataigne",
        "image_url": "https://static.openfoodfacts.org/images/products/376/007/201/0204/front_fr.13.400.jpg",
        "image_small_url": "https://static.openfoodfacts.org/images/products/376/007/201/0204/front_fr.13.200.jpg",
        "fat": "moderate",
        "salt": "low",
        "saturated_fat": "moderate",
        "sugars": "high",
        "fat_100g": 10,
        "saturated_fat_100g": 2,
        "sugars_100g": 48,
        "salt_100g": 0
    }
},
{
    "model": "product.product",
    "pk": 16809,
    "fields": {
        "code": "3760010099100",
        "product_name": "Basquella",
        "brands": "Miguelgorry",
        "categories": "Petit-d\u00e9jeuners,Produits \u00e0 tartiner,Produits \u00e0 tartiner sucr\u00e9s,P\u00e2tes \u00e0 tartiner,P\u00e2tes \u00e0 tartiner au chocolat,P\u00e2tes \u00e0 tartiner aux noisettes,P\u00e2tes \u00e0 tartiner aux noisettes et au cacao",
        "nutrition_grades": "e",
        "url": "https://fr.openfoodfacts.org/produit/3760010099100/basquella-miguelgorry",
        "image_url": "https://static.openfoodfacts.org/images/products/376/001/009/9100/front_fr.17.400.jpg",
        "image_small_url": "https://static.openfoodfacts.org/images/products/376/001/009/9100/front_fr.17.200.jpg",
        "fat": "high",
        "salt": "low",
        "saturated_fat": "high",
        "sugars": "high",
        "fat_100g": 28,
        "saturated_fat_100g": 6,
        "sugars_100g": 58,
        "salt_100g": 0
    }
},
{
    "model": "product.product",
    "pk": 16808,
    "fields": {
        "code": "3770003801122",
        "product_name": "Nucellina",
        "brands": "Florence Marsili",
        "categories": "Petit-d\u00e9jeuners,Produits \u00e0 tartiner,Produits \u00e0 tartiner sucr\u00e9s,P\u00e2tes \u00e0 tartiner,P\u00e2tes \u00e0 tartiner au chocolat,P\u00e2tes \u00e0 tartiner aux noisettes,P\u00e2tes \u00e0 tartiner aux noisettes et au cacao",
        "nutrition_grades": "e",
        "url": "https://fr.openfoodfacts.org/produit/3770003801122/nucellina-florence-marsili",
        "image_url": "https://static.openfoodfacts.org/images/products/377/000/380/1122/front_fr.4.400.jpg",
        "image_small_url": "https://static.openfoodfacts.org/images/products/377/000/380/1122/front_fr.4.200.jpg",
        "fat": "high",
        "salt": "low",
        "saturated_fat": "high",
        "sugars": "high",
        "fat_100g": 38,
        "saturated_fat_100g": 9,
        "sugars_100g": 47,
        "salt_100g": 0
    }
},
{
    "model": "product.product",
    "pk": 16805,
    "fields": {
        "code": "3535800940005",
        "product_name": "P\u00e2te Croustillante aux \u00c9clats de Cr\u00eape Dentelle",
        "brands": "Gavottes",
        "categories": "Petit-d\u00e9jeuners,Produits \u00e0 tartiner,Produits \u00e0 tartiner sucr\u00e9s,P\u00e2tes \u00e0 tartiner,P\u00e2tes \u00e0 tartiner au chocolat,P\u00e2tes \u00e0 tartiner aux noisettes,P\u00e2tes \u00e0 tartiner aux noisettes et au cacao",
        "nutrition_grades": "e",
        "url": "https://fr.openfoodfacts.org/produit/3535800940005/pate-croustillante-aux-eclats-de-crepe-dentelle-gavottes",
        "image_url": "https://static.openfoodfacts.org/images/products/353/580/094/0005/front_fr.17.400.jpg",
        "image_small_url": "https://static.openfoodfacts.org/images/products/353/580/094/0005/front_fr.17.200.jpg",
        "fat": "high",
        "salt": "moderate",
        "saturated_fat": "high",
        "sugars": "high",
        "fat_100g": 37,
        "saturated_fat_100g": 9,
        "sugars_100g": 48,
        "salt_100g": 0
    }
},
{
    "model": "product.product",
    "pk": 16307,
    "fields": {
        "code": "3250392397029",
        "product_name": "La P\u00e2te \u00e0 Tartiner",
        "brands": "Ivoria",
        "categories": "Petit-d\u00e9jeuners,Produits \u00e0 tartiner,Produits \u00e0 tartiner sucr\u00e9s,P\u00e2tes \u00e0 tartiner,P\u00e2tes \u00e0 tartiner au chocolat,P\u00e2tes \u00e0 tartiner aux noisettes,P\u00e2tes \u00e0 tartiner aux noisettes et au cacao",
        "nutrition_grades": "e",
        "url": "https://fr.openfoodfacts.org/produit/3250392397029/la-pate-a-tartiner-ivoria",
        "image_url": "https://static.openfoodfacts.org/images/products/325/039/239/7029/front_fr.22.400.jpg",
        "image_small_url": "https://static.openfoodfacts.org/images/products/325/039/239/7029/front_fr.22.200.jpg",
        "fat": "high",
        "salt": "low",
        "saturated_fat": "high",
        "sugars": "high",
        "fat_100g": 32,
        "saturated_fat_100g": 6,
        "sugars_100g": 54,
        "salt_100g": 0
    }
},
{
    "model": "product.product",
    "pk": 16256,
    "fields": {
        "code": "3330720237781",
        "product_name": "P\u00e2te \u00e0 tartiner de No\u00ebl",
        "brands": "Lucien Georgelin",
        "categories": "Petit-d\u00e9jeuners,Produits \u00e0 tartiner,Produits \u00e0 tartiner sucr\u00e9s,P\u00e2tes \u00e0 tartiner,P\u00e2tes \u00e0 tartiner au chocolat,P\u00e2tes \u00e0 tartiner aux noisettes,P\u00e2tes \u00e0 tartiner aux noisettes et au cacao",
        "nutrition_grades": "e",
        "url": "https://fr.openfoodfacts.org/produit/3330720237781/pate-a-tartiner-de-noel-lucien-georgelin",
        "image_url": "https://static.openfoodfacts.org/images/products/333/072/023/7781/front_fr.8.400.jpg",
        "image_small_url": "https://static.openfoodfacts.org/images/products/333/072/023/7781/front_fr.8.200.jpg",
        "fat": "high",
        "salt": "low",
        "saturated_fat": "high",
        "sugars": "high",
        "fat_100g": 32,
        "saturated_fat_100g": 10,
        "sugars_100g": 46,
        "salt_100g": 0
    }
},
{
    "model": "product.product",
    "pk": 15193,
    "fields": {
        "code": "3760076003042",
        "product_name": "Choko noisette",
        "brands": "Noiseraie Productions",
        "categories": "Petit-d\u00e9jeuners,Produits \u00e0 tartiner,Produits \u00e0 tartiner sucr\u00e9s,P\u00e2tes \u00e0 tartiner,P\u00e2tes \u00e0 tartiner au chocolat,P\u00e2tes \u00e0 tartiner aux noisettes,P\u00e2tes \u00e0 tartiner aux noisettes et au cacao",
        "nutrition_grades": "d",
        "url": "https://fr.openfoodfacts.org/produit/3760076003042/choko-noisette-noiseraie-productions",
        "image_url": "https://static.openfoodfacts.org/images/products/376/007/600/3042/front_fr.4.400.jpg",
        "image_small_url": "https://static.openfoodfacts.org/images/products/376/007/600/3042/front_fr.4.200.jpg",
        "fat": "high",
        "salt": "low",
        "saturated_fat": "high",
        "sugars": "high",
        "fat_100g": 42,
        "saturated_fat_100g": 6,
        "sugars_100g": 44,
        "salt_100g": 0
    }
},
{
    "model": "product.product",
    "pk": 14943,
    "fields": {
        "code": "3564700859032",
        "product_name": "Pate a tartiner aux noisettes",
        "brands": "Marque Rep\u00e8re,Leclerc",
        "categories": "Produits \u00e0 tartiner,Petit-d\u00e9jeuners,Produits \u00e0 tartiner sucr\u00e9s,P\u00e2tes \u00e0 tartiner,P\u00e2tes \u00e0 tartiner au chocolat,P\u00e2tes \u00e0 tartiner aux noisettes,P\u00e2tes \u00e0 tartiner aux noisettes et au cacao",
        "nutrition_grades": "e",
        "url": "https://fr.openfoodfacts.org/produit/3564700859032/pate-a-tartiner-aux-noisettes-marque-repere",
        "image_url": "https://static.openfoodfacts.org/images/products/356/470/085/9032/front_fr.4.400.jpg",
        "image_small_url": "https://static.openfoodfacts.org/images/products/356/470/085/9032/front_fr.4.200.jpg",
        "fat": "high",
        "salt": "low",
        "saturated_fat": "high",
        "sugars": "high",
        "fat_100g": 29,
        "saturated_fat_100g": 10,
        "sugars_100g": 58,
        "salt_100g": 0
    }
},
{
    "model": "product.product",
    "pk": 14898,
    "fields": {
        "code": "3560071005672",
        "product_name": "P\u00e2te \u00e0 tartiner aux noisettes",
        "brands": "Carrefour",
        "categories": "Produits \u00e0 tartiner,Petit-d\u00e9jeuners,Produits \u00e0 tartiner sucr\u00e9s,P\u00e2tes \u00e0 tartiner,P\u00e2tes \u00e0 tartiner au chocolat,P\u00e2tes \u00e0 tartiner aux noisettes,P\u00e2tes \u00e0 tartiner aux noisettes et au cacao",
        "nutrition_grades": "e",
        "url": "https://fr.openfoodfacts.org/produit/3560071005672/pate-a-tartiner-aux-noisettes-carrefour",
        "image_url": "https://static.openfoodfacts.org/images/products/356/007/100/5672/front_fr.6.400.jpg",
        "image_small_url": "https://static.openfoodfacts.org/images/products/356/007/100/5672/front_fr.6.200.jpg",
        "fat": "high",
        "salt": "low",
        "saturated_fat": "high",
        "sugars": "high",
        "fat_100g": 29,
        "saturated_fat_100g": 10,
        "sugars_100g": 57,
        "salt_100g": 0
    }
},
{
    "model": "product.product",
    "pk": 14488,
    "fields": {
        "code": "8002352365006",
        "product_name": "Chocobella",
        "brands": "Damiano",
        "categories": "Petit-d\u00e9jeuners,Produits \u00e0 tartiner,Produits \u00e0 tartiner sucr\u00e9s,P\u00e2tes \u00e0 tartiner,P\u00e2tes \u00e0 tartiner au chocolat,P\u00e2tes \u00e0 tartiner aux noisettes,P\u00e2tes \u00e0 tartiner aux noisettes et au cacao",
        "nutrition_grades": "e",
        "url": "https://fr.openfoodfacts.org/produit/8002352365006/chocobella-damiano",
        "image_url": "https://static.openfoodfacts.org/images/products/800/235/236/5006/front_fr.7.400.jpg",
        "image_small_url": "https://static.openfoodfacts.org/images/products/800/235/236/5006/front_fr.7.200.jpg",
        "fat": "high",
        "salt": "low",
        "saturated_fat": "high",
        "sugars": "high",
        "fat_100g": 30,
        "saturated_fat_100g": 10,
        "sugars_100g": 47,
        "salt_100g": 0
    }
},
{
    "model": "product.product",
    "pk": 11014,
    "fields": {
        "code": "3368959012510",
        "product_name": "Pate \u00e0 tartiner au chocolat noir noisettes",
        "brands": "U Saveurs, U",
        "categories": "Petit-d\u00e9jeuners,Produits \u00e0 tartiner,Produits \u00e0 tartiner sucr\u00e9s,P\u00e2tes \u00e0 tartiner,P\u00e2tes \u00e0 tartiner au chocolat,P\u00e2tes \u00e0 tartiner aux noisettes,P\u00e2tes \u00e0 tartiner aux noisettes et au cacao,Epicerie sal\u00e9e",
        "nutrition_grades": "d",
        "url": "https://fr.openfoodfacts.org/produit/3368959012510/pate-a-tartiner-au-chocolat-noir-noisettes-u-saveurs",
        "image_url": "https://static.openfoodfacts.org/images/products/336/895/901/2510/front_fr.25.400.jpg",
        "image_small_url": "https://static.openfoodfacts.org/images/products/336/895/901/2510/front_fr.25.200.jpg",
        "fat": "high",
        "salt": "low",
        "saturated_fat": "high",
        "sugars": "high",
        "fat_100g": 48,
        "saturated_fat_100g": 10,
        "sugars_100g": 32,
        "salt_100g": 0
    }
},
{
    "model": "product.product",
    "pk": 9838,
    "fields": {
        "code": "3760076003059",
        "product_name": "Choko Noisette Sans Palme",
        "brands": "Noiseraie Productions",
        "categories": "Petit-d\u00e9jeuners,Produits \u00e0 tartiner,Produits \u00e0 tartiner sucr\u00e9s,P\u00e2tes \u00e0 tartiner,P\u00e2tes \u00e0 tartiner au chocolat,P\u00e2tes \u00e0 tartiner aux noisettes,P\u00e2tes \u00e0 tartiner aux noisettes et au cacao",
        "nutrition_grades": "e",
        "url": "https://fr.openfoodfacts.org/produit/3760076003059/choko-noisette-sans-palme-noiseraie-productions",
        "image_url": "https://static.openfoodfacts.org/images/products/376/007/600/3059/front_fr.12.400.jpg",
        "image_small_url": "https://static.openfoodfacts.org/images/products/376/007/600/3059/front_fr.12.200.jpg",
        "fat": "high",
        "salt": "low",
        "saturated_fat": "high",
        "sugars": "high",
        "fat_100g": 41,
        "saturated_fat_100g": 11,
        "sugars_100g": 43,
        "salt_100g": 0
    }
},
{
    "model": "product.product",
    "pk": 8342,
    "fields": {
        "code": "3560070756100",
        "product_name": "P\u00e2te \u00e0 tartiner noisettes",
        "brands": "Grand Jury",
        "categories": "Petit-d\u00e9jeuners,Produits \u00e0 tartiner,Produits \u00e0 tartiner sucr\u00e9s,P\u00e2tes \u00e0 tartiner,P\u00e2tes \u00e0 tartiner au chocolat,P\u00e2tes \u00e0 tartiner aux noisettes,P\u00e2tes \u00e0 tartiner aux noisettes et au cacao",
        "nutrition_grades": "e",
        "url": "https://fr.openfoodfacts.org/produit/3560070756100/pate-a-tartiner-noisettes-grand-jury",
        "image_url": "https://static.openfoodfacts.org/images/products/356/007/075/6100/front_fr.15.400.jpg",
        "image_small_url": "https://static.openfoodfacts.org/images/products/356/007/075/6100/front_fr.15.200.jpg",
        "fat": "high",
        "salt": "low",
        "saturated_fat": "high",
        "sugars": "high",
        "fat_100g": 29,
        "saturated_fat_100g": 10,
        "sugars_100g": 57,
        "salt_100g": 0
    }
},
{
    "model": "product.product",
    "pk": 8020,
    "fields": {
        "code": "3350033468863",
        "product_name": "Pate a tartiner bio",
        "brands": "Monoprix",
        "categories": "Petit-d\u00e9jeuners,Produits \u00e0 tartiner,Produits \u00e0 tartiner sucr\u00e9s,P\u00e2tes \u00e0 tartiner,P\u00e2tes \u00e0 tartiner au chocolat,P\u00e2tes \u00e0 tartiner aux noisettes,P\u00e2tes \u00e0 tartiner aux noisettes et au cacao",
        "nutrition_grades": "d",
        "url": "https://fr.openfoodfacts.org/produit/3350033468863/pate-a-tartiner-bio-monoprix",
        "image_url": "https://static.openfoodfacts.org/images/products/335/003/346/8863/front_fr.4.400.jpg",
        "image_small_url": "https://static.openfoodfacts.org/images/products/335/003/346/8863/front_fr.4.200.jpg",
        "fat": "high",
        "salt": "low",
        "saturated_fat": "high",
        "sugars": "high",
        "fat_100g": 30,
        "saturated_fat_100g": 5,
        "sugars_100g": 54,
        "salt_100g": 0
    }
},
{
    "model": "product.product",
    "pk": 7082,
    "fields": {
        "code": "3250391660995",
        "product_name": "P\u00e2te \u00e0 tartiner aux noisettes et au cacao bio",
        "brands": "Ivoria",
        "categories": "Petit-d\u00e9jeuners,Produits \u00e0 tartiner,Produits \u00e0 tartiner sucr\u00e9s,P\u00e2tes \u00e0 tartiner,P\u00e2tes \u00e0 tartiner au chocolat,P\u00e2tes \u00e0 tartiner aux noisettes,P\u00e2tes \u00e0 tartiner aux noisettes et au cacao",
        "nutrition_grades": "e",
        "url": "https://fr.openfoodfacts.org/produit/3250391660995/pate-a-tartiner-aux-noisettes-et-au-cacao-bio-ivoria",
        "image_url": "https://static.openfoodfacts.org/images/products/325/039/166/0995/front_fr.43.400.jpg",
        "image_small_url": "https://static.openfoodfacts.org/images/products/325/039/166/0995/front_fr.43.200.jpg",
        "fat": "high",
        "salt": "low",
        "saturated_fat": "high",
        "sugars": "high",
        "fat_100g": 30,
        "saturated_fat_100g": 7,
        "sugars_100g": 56,
        "salt_100g": 0
    }
},
{
    "model": "product.product",
    "pk": 6467,
    "fields": {
        "code": "3396411222146",
        "product_name": "P\u00e2te \u00e0 tartiner Cacao Noisette",
        "brands": "Bonneterre",
        "categories": "Petit-d\u00e9jeuners,Produits \u00e0 tartiner,Produits \u00e0 tartiner sucr\u00e9s,P\u00e2tes \u00e0 tartiner,P\u00e2tes \u00e0 tartiner au chocolat,P\u00e2tes \u00e0 tartiner aux noisettes,P\u00e2tes \u00e0 tartiner aux noisettes et au cacao",
        "nutrition_grades": "e",
        "url": "https://fr.openfoodfacts.org/produit/3396411222146/pate-a-tartiner-cacao-noisette-bonneterre",
        "image_url": "https://static.openfoodfacts.org/images/products/339/641/122/2146/front_fr.29.400.jpg",
        "image_small_url": "https://static.openfoodfacts.org/images/products/339/641/122/2146/front_fr.29.200.jpg",
        "fat": "high",
        "salt": "low",
        "saturated_fat": "high",
        "sugars": "high",
        "fat_100g": 37,
        "saturated_fat_100g": 9,
        "sugars_100g": 51,
        "salt_100g": 0
    }
},
{
    "model": "product.product",
    "pk": 6441,
    "fields": {
        "code": "20554729",
        "product_name": "P\u00e2te \u00e0 Tartiner",
        "brands": "Choco Nussa",
        "categories": "Petit-d\u00e9jeuners,Produits \u00e0 tartiner,Produits \u00e0 tartiner sucr\u00e9s,P\u00e2tes \u00e0 tartiner,P\u00e2tes \u00e0 tartiner au chocolat,P\u00e2tes \u00e0 tartiner aux noisettes,P\u00e2tes \u00e0 tartiner aux noisettes et au cacao",
        "nutrition_grades": "d",
        "url": "https://fr.openfoodfacts.org/produit/20554729/pate-a-tartiner-choco-nussa",
        "image_url": "https://static.openfoodfacts.org/images/products/20554729/front_fr.13.400.jpg",
        "image_small_url": "https://static.openfoodfacts.org/images/products/20554729/front_fr.13.200.jpg",
        "fat": "high",
        "salt": "low",
        "saturated_fat": "high",
        "sugars": "high",
        "fat_100g": 34,
        "saturated_fat_100g": 6,
        "sugars_100g": 53,
        "salt_100g": 0
    }
},
{
    "model": "product.product",
    "pk": 5719,
    "fields": {
        "code": "3700477609498",
        "product_name": "P\u00e2te \u00e0 tartiner chocolat noisettes",
        "brands": "Mamie Bio",
        "categories": "Petit-d\u00e9jeuners,Produits \u00e0 tartiner,Produits \u00e0 tartiner sucr\u00e9s,P\u00e2tes \u00e0 tartiner,P\u00e2tes \u00e0 tartiner au chocolat,P\u00e2tes \u00e0 tartiner aux noisettes,P\u00e2tes \u00e0 tartiner aux noisettes et au cacao",
        "nutrition_grades": "d",
        "url": "https://fr.openfoodfacts.org/produit/3700477609498/pate-a-tartiner-chocolat-noisettes-mamie-bio",
        "image_url": "https://static.openfoodfacts.org/images/products/370/047/760/9498/front_fr.17.400.jpg",
        "image_small_url": "https://static.openfoodfacts.org/images/products/370/047/760/9498/front_fr.17.200.jpg",
        "fat": "high",
        "salt": "low",
        "saturated_fat": "high",
        "sugars": "high",
        "fat_100g": 34,
        "saturated_fat_100g": 6,
        "sugars_100g": 52,
        "salt_100g": 0
    }
},
{
    "model": "product.product",
    "pk": 5704,
    "fields": {
        "code": "3017620421006",
        "product_name": "Nutella",
        "brands": "Ferrero",
        "categories": "Petit-d\u00e9jeuners,Produits \u00e0 tartiner,Produits \u00e0 tartiner sucr\u00e9s,P\u00e2tes \u00e0 tartiner,P\u00e2tes \u00e0 tartiner au chocolat,P\u00e2tes \u00e0 tartiner aux noisettes,P\u00e2tes \u00e0 tartiner aux noisettes et au cacao",
        "nutrition_grades": "e",
        "url": "https://fr.openfoodfacts.org/produit/3017620421006/nutella-ferrero",
        "image_url": "https://static.openfoodfacts.org/images/products/301/762/042/1006/front_fr.87.400.jpg",
        "image_small_url": "https://static.openfoodfacts.org/images/products/301/762/042/1006/front_fr.87.200.jpg",
        "fat": "high",
        "salt": "low",
        "saturated_fat": "high",
        "sugars": "high",
        "fat_100g": 31,
        "saturated_fat_100g": 11,
        "sugars_100g": 56,
        "salt_100g": 0
    }
},
{
    "model": "product.product",
    "pk": 5470,
    "fields": {
        "code": "3760074419586",
        "product_name": "Nutrabreizh",
        "brands": "Nutabreizh",
        "categories": "Petit-d\u00e9jeuners,Produits \u00e0 tartiner,Produits \u00e0 tartiner sucr\u00e9s,P\u00e2tes \u00e0 tartiner,P\u00e2tes \u00e0 tartiner au chocolat,P\u00e2tes \u00e0 tartiner aux noisettes,P\u00e2tes \u00e0 tartiner aux noisettes et au cacao",
        "nutrition_grades": "e",
        "url": "https://fr.openfoodfacts.org/produit/3760074419586/nutrabreizh-nutabreizh",
        "image_url": "https://static.openfoodfacts.org/images/products/376/007/441/9586/front_fr.20.400.jpg",
        "image_small_url": "https://static.openfoodfacts.org/images/products/376/007/441/9586/front_fr.20.200.jpg",
        "fat": "high",
        "salt": "low",
        "saturated_fat": "high",
        "sugars": "high",
        "fat_100g": 32,
        "saturated_fat_100g": 16,
        "sugars_100g": 36,
        "salt_100g": 0
    }
},
{
    "model": "product.product",
    "pk": 5247,
    "fields": {
        "code": "3560070472888",
        "product_name": "P\u00e2te \u00e0 tartiner aux noisettes",
        "brands": "Carrefour Bio,Carrefour",
        "categories": "Petit-d\u00e9jeuners,Produits \u00e0 tartiner,Produits \u00e0 tartiner sucr\u00e9s,P\u00e2tes \u00e0 tartiner,P\u00e2tes \u00e0 tartiner au chocolat,P\u00e2tes \u00e0 tartiner aux noisettes,P\u00e2tes \u00e0 tartiner aux noisettes et au cacao",
        "nutrition_grades": "d",
        "url": "https://fr.openfoodfacts.org/produit/3560070472888/pate-a-tartiner-aux-noisettes-carrefour-bio",
        "image_url": "https://static.openfoodfacts.org/images/products/356/007/047/2888/front_fr.25.400.jpg",
        "image_small_url": "https://static.openfoodfacts.org/images/products/356/007/047/2888/front_fr.25.200.jpg",
        "fat": "high",
        "salt": "low",
        "saturated_fat": "moderate",
        "sugars": "high",
        "fat_100g": 29,
        "saturated_fat_100g": 3,
        "sugars_100g": 59,
        "salt_100g": 0
    }
},
{
    "model": "product.product",
    "pk": 3193,
    "fields": {
        "code": "3330720237361",
        "product_name": "P\u00e2te a tartiner",
        "brands": "Lucien Georgelin",
        "categories": "Petit-d\u00e9jeuners,Produits \u00e0 tartiner,Produits \u00e0 tartiner sucr\u00e9s,P\u00e2tes \u00e0 tartiner,P\u00e2tes \u00e0 tartiner au chocolat,P\u00e2tes \u00e0 tartiner aux noisettes,P\u00e2tes \u00e0 tartiner aux noisettes et au cacao",
        "nutrition_grades": "e",
        "url": "https://fr.openfoodfacts.org/produit/3330720237361/pate-a-tartiner-lucien-georgelin",
        "image_url": "https://static.openfoodfacts.org/images/products/333/072/023/7361/front_fr.64.400.jpg",
        "image_small_url": "https://static.openfoodfacts.org/images/products/333/072/023/7361/front_fr.64.200.jpg",
        "fat": "high",
        "salt": "low",
        "saturated_fat": "high",
        "sugars": "high",
        "fat_100g": 32,
        "saturated_fat_100g": 10,
        "sugars_100g": 50,
        "salt_100g": 0
    }
},
{
    "model": "product.product",
    "pk": 2754,
    "fields": {
        "code": "3330720237255",
        "product_name": "P\u00e2te \u00e0 tartiner Bio",
        "brands": "Lucien Georgelin",
        "categories": "Petit-d\u00e9jeuners,Produits \u00e0 tartiner,Produits \u00e0 tartiner sucr\u00e9s,P\u00e2tes \u00e0 tartiner,P\u00e2tes \u00e0 tartiner au chocolat,P\u00e2tes \u00e0 tartiner aux noisettes,P\u00e2tes \u00e0 tartiner aux noisettes et au cacao",
        "nutrition_grades": "e",
        "url": "https://fr.openfoodfacts.org/produit/3330720237255/pate-a-tartiner-bio-lucien-georgelin",
        "image_url": "https://static.openfoodfacts.org/images/products/333/072/023/7255/front_fr.25.400.jpg",
        "image_small_url": "https://static.openfoodfacts.org/images/products/333/072/023/7255/front_fr.25.200.jpg",
        "fat": "high",
        "salt": "low",
        "saturated_fat": "high",
        "sugars": "high",
        "fat_100g": 35,
        "saturated_fat_100g": 17,
        "sugars_100g": 49,
        "salt_100g": 0
    }
},
{
    "model": "product.product",
    "pk": 2577,
    "fields": {
        "code": "3330720237378",
        "product_name": "Pate a tartiner",
        "brands": "Lucien Georgelin",
        "categories": "Petit-d\u00e9jeuners,Produits \u00e0 tartiner,Produits \u00e0 tartiner sucr\u00e9s,P\u00e2tes \u00e0 tartiner,P\u00e2tes \u00e0 tartiner au chocolat,P\u00e2tes \u00e0 tartiner aux noisettes,P\u00e2tes \u00e0 tartiner aux noisettes et au cacao",
        "nutrition_grades": "e",
        "url": "https://fr.openfoodfacts.org/produit/3330720237378/pate-a-tartiner-lucien-georgelin",
        "image_url": "https://static.openfoodfacts.org/images/products/333/072/023/7378/front_fr.27.400.jpg",
        "image_small_url": "https://static.openfoodfacts.org/images/products/333/072/023/7378/front_fr.27.200.jpg",
        "fat": "high",
        "salt": "low",
        "saturated_fat": "high",
        "sugars": "high",
        "fat_100g": 35,
        "saturated_fat_100g": 17,
        "sugars_100g": 49,
        "salt_100g": 0
    }
},
{
    "model": "product.product",
    "pk": 2487,
    "fields": {
        "code": "3478820023184",
        "product_name": "P\u00e2te \u00e0 tartiner chocolat noisette",
        "brands": "Jardin Bio",
        "categories": "Petit-d\u00e9jeuners,Produits \u00e0 tartiner,Produits \u00e0 tartiner sucr\u00e9s,P\u00e2tes \u00e0 tartiner,P\u00e2tes \u00e0 tartiner au chocolat,P\u00e2tes \u00e0 tartiner aux noisettes,P\u00e2tes \u00e0 tartiner aux noisettes et au cacao",
        "nutrition_grades": "d",
        "url": "https://fr.openfoodfacts.org/produit/3478820023184/pate-a-tartiner-chocolat-noisette-jardin-bio",
        "image_url": "https://static.openfoodfacts.org/images/products/347/882/002/3184/front_fr.82.400.jpg",
        "image_small_url": "https://static.openfoodfacts.org/images/products/347/882/002/3184/front_fr.82.200.jpg",
        "fat": "high",
        "salt": "low",
        "saturated_fat": "high",
        "sugars": "high",
        "fat_100g": 34,
        "saturated_fat_100g": 6,
        "sugars_100g": 52,
        "salt_100g": 0
    }
},
{
    "model": "product.product",
    "pk": 2426,
    "fields": {
        "code": "27035849",
        "product_name": "Snack'n Play Toys",
        "brands": "Delinut",
        "categories": "Petit-d\u00e9jeuners,Produits \u00e0 tartiner,Produits \u00e0 tartiner sucr\u00e9s,P\u00e2tes \u00e0 tartiner,P\u00e2tes \u00e0 tartiner au chocolat,P\u00e2tes \u00e0 tartiner aux noisettes,P\u00e2tes \u00e0 tartiner aux noisettes et au cacao",
        "nutrition_grades": "e",
        "url": "https://fr.openfoodfacts.org/produit/27035849/snack-n-play-toys-delinut",
        "image_url": "https://static.openfoodfacts.org/images/products/27035849/front_fr.18.400.jpg",
        "image_small_url": "https://static.openfoodfacts.org/images/products/27035849/front_fr.18.200.jpg",
        "fat": "high",
        "salt": "moderate",
        "saturated_fat": "high",
        "sugars": "high",
        "fat_100g": 27,
        "saturated_fat_100g": 6,
        "sugars_100g": 36,
        "salt_100g": 1
    }
},
{
    "model": "product.product",
    "pk": 1729,
    "fields": {
        "code": "80809180",
        "product_name": "Mini Nutella",
        "brands": "Ferrero",
        "categories": "Petit-d\u00e9jeuners,Produits \u00e0 tartiner,Produits \u00e0 tartiner sucr\u00e9s,P\u00e2tes \u00e0 tartiner,P\u00e2tes \u00e0 tartiner au chocolat,P\u00e2tes \u00e0 tartiner aux noisettes,P\u00e2tes \u00e0 tartiner aux noisettes et au cacao",
        "nutrition_grades": "e",
        "url": "https://fr.openfoodfacts.org/produit/80809180/mini-nutella-ferrero",
        "image_url": "https://static.openfoodfacts.org/images/products/80809180/front_fr.34.400.jpg",
        "image_small_url": "https://static.openfoodfacts.org/images/products/80809180/front_fr.34.200.jpg",
        "fat": "high",
        "salt": "low",
        "saturated_fat": "high",
        "sugars": "high",
        "fat_100g": 31,
        "saturated_fat_100g": 11,
        "sugars_100g": 56,
        "salt_100g": 0
    }
},
{
    "model": "product.product",
    "pk": 1484,
    "fields": {
        "code": "3700477609504",
        "product_name": "Pate \u00e0 tartiner aux noisettes",
        "brands": "Mamie Bio",
        "categories": "Petit-d\u00e9jeuners,Produits \u00e0 tartiner,Produits \u00e0 tartiner sucr\u00e9s,P\u00e2tes \u00e0 tartiner,P\u00e2tes \u00e0 tartiner au chocolat,P\u00e2tes \u00e0 tartiner aux noisettes,P\u00e2tes \u00e0 tartiner aux noisettes et au cacao",
        "nutrition_grades": "d",
        "url": "https://fr.openfoodfacts.org/produit/3700477609504/pate-a-tartiner-aux-noisettes-mamie-bio",
        "image_url": "https://static.openfoodfacts.org/images/products/370/047/760/9504/front_fr.13.400.jpg",
        "image_small_url": "https://static.openfoodfacts.org/images/products/370/047/760/9504/front_fr.13.200.jpg",
        "fat": "high",
        "salt": "low",
        "saturated_fat": "high",
        "sugars": "high",
        "fat_100g": 35,
        "saturated_fat_100g": 6,
        "sugars_100g": 52,
        "salt_100g": 0
    }
},
{
    "model": "product.product",
    "pk": 1334,
    "fields": {
        "code": "3596710333936",
        "product_name": "P\u00e2te \u00e0 Tartiner Noisettes et Cacao",
        "brands": "Auchan Bio,Auchan",
        "categories": "Petit-d\u00e9jeuners,Produits \u00e0 tartiner,Produits \u00e0 tartiner sucr\u00e9s,P\u00e2tes \u00e0 tartiner,P\u00e2tes \u00e0 tartiner au chocolat,P\u00e2tes \u00e0 tartiner aux noisettes,P\u00e2tes \u00e0 tartiner aux noisettes et au cacao",
        "nutrition_grades": "e",
        "url": "https://fr.openfoodfacts.org/produit/3596710333936/pate-a-tartiner-noisettes-et-cacao-auchan-bio",
        "image_url": "https://static.openfoodfacts.org/images/products/359/671/033/3936/front_fr.21.400.jpg",
        "image_small_url": "https://static.openfoodfacts.org/images/products/359/671/033/3936/front_fr.21.200.jpg",
        "fat": "high",
        "salt": "low",
        "saturated_fat": "high",
        "sugars": "high",
        "fat_100g": 37,
        "saturated_fat_100g": 9,
        "sugars_100g": 51,
        "salt_100g": 0
    }
},
{
    "model": "product.product",
    "pk": 1042,
    "fields": {
        "code": "3564707104920",
        "product_name": "P\u00e2te \u00e0 tartiner bio village",
        "brands": "Bio Village,Marque Rep\u00e8re",
        "categories": "Petit-d\u00e9jeuners,Produits \u00e0 tartiner,Produits \u00e0 tartiner sucr\u00e9s,P\u00e2tes \u00e0 tartiner,P\u00e2tes \u00e0 tartiner au chocolat,P\u00e2tes \u00e0 tartiner aux noisettes,P\u00e2tes \u00e0 tartiner aux noisettes et au cacao",
        "nutrition_grades": "d",
        "url": "https://fr.openfoodfacts.org/produit/3564707104920/pate-a-tartiner-bio-village",
        "image_url": "https://static.openfoodfacts.org/images/products/356/470/710/4920/front_fr.27.400.jpg",
        "image_small_url": "https://static.openfoodfacts.org/images/products/356/470/710/4920/front_fr.27.200.jpg",
        "fat": "high",
        "salt": "low",
        "saturated_fat": "high",
        "sugars": "high",
        "fat_100g": 29,
        "saturated_fat_100g": 6,
        "sugars_100g": 52,
        "salt_100g": 0
    }
}
]
